Workbook

Sheet Leia-me
A1: DairyUp - Modelo financeiro (60 meses)
A3: RESUMO EXECUTIVO (cenário base, valores gerados pelo modelo)
A4: Sistema de gestão da qualidade do leite e do rebanho (DairyUp), assinatura por vaca/mês. Ano 5: 860 fazendas, 146.191 vacas, ARR de R$ 19.456.171, EBITDA de R$ 4.993.036.
A5: Aporte solicitado: R$ 4.700.000 (3 parcelas por marcos). Necessidade máxima de caixa: R$ 4.044.057. Break-even operacional no mês 32; payback no mês 54.
A6: VPL com valor residual: R$ 7.476.441; sem valor residual: R$ -226.236. TIR sem valor residual: 22%.
A7: Decisão: aprovar o investimento e o lançamento comercial no mês 4. Detalhes: aba Anual, Retornos e Cenários e sensibilidade.
A9: Planilha-mestre do plano de negócios. Todos os números do deck e do documento vêm daqui.
A11: COMO USAR
A12: 1) Edite apenas as células em AZUL com fundo AMARELO na aba "Premissas". Todas as demais abas são fórmulas.
A13: 2) Para trocar de cenário, altere "Cenário ativo" (1 = Conservador, 2 = Base, 3 = Otimista) na aba Premissas.
A14: 3) A aba "Cenários e sensibilidade" guarda resultados já calculados (valores) dos 3 cenários e das grades de sensibilidade; para atualizá-los depois de mudar premissas, altere o cenário e leia as abas Anual/Retornos.
A16: ABAS
... A26: Simplificações: sem depreciação, juros e imposto sobre lucro (carga tributária incide sobre a receita); desenvolvimento tratado como despesa (sem capitalização); caixa sem rendimento financeiro.

Sheet Premissas
A1: Premissas (edite as células azuis/amarelas)
A3: Premissa | B3: Valor | C3: Unidade | D3: Fonte / observação
A4: Geral
A5: Mês de lançamento comercial (1º cliente pagante) | B5: 4 | C5: mês | D5: Marco: MVP endurecido + 3 pilotos concluídos. Premissa de projeto.
A6: Reajuste anual de preços e salários (IPCA) | B6: 0.05 | C6: % a.a. | D6: Premissa; aplicado a partir do ano 2.
A7: Prazo médio de recebimento | B7: 10 | C7: dias | D7: Cobrança mensal antecipada via boleto/PIX; premissa.
A8: Prazo médio de pagamento (fornecedores e encargos) | B8: 20 | C8: dias | D8: Premissa.
A9: Taxa de desconto (TMA) para VPL | B9: 0.25 | C9: % a.a. | D9: Premissa de custo de capital de risco para startup de software (Selic + prêmio).
A10: Múltiplo de valor residual (EV / receita líquida do ano 5) | B10: 1.5 | C10: x | D10: Premissa conservadora para SaaS vertical; o VPL é mostrado também SEM valor residual.
A11: Preços (por plano)
A12: Mix de fazendas - Essencial | B12: 0.5 | C12: % | D12: Premissa. Mix soma 100%.
A13: Mix de fazendas - Profissional | B13: 0.38 | C13: % | D13: Premissa.
A14: Mix de fazendas - Premium | B14: =1-mix_ess-mix_pro -> 0.12 | C14: % | D14: Calculado: 100% - demais.
A15: Vacas em lactação por fazenda - Essencial | B15: 80 | C15: vacas | D15: Premissa: pequeno porte (até ~120 vacas).
A16: Vacas em lactação por fazenda - Profissional | B16: 200 | C16: vacas | D16: Premissa: médio porte (120 a 400). Piloto Mariana: ~300-400 vacas.
A17: Vacas em lactação por fazenda - Premium | B17: 450 | C17: vacas | D17: Premissa: grande porte (acima de 400).
A18: Preço Essencial por vaca/mês | B18: 4.5 | C18: R$/vaca/mês | D18: Premissa; a validar com 10 entrevistas de preço (ver plano).
A19: Preço Profissional por vaca/mês | B19: 7 | C19: R$/vaca/mês | D19: Premissa.
A20: Preço Premium por vaca/mês | B20: 10 | C20: R$/vaca/mês | D20: Premissa.
A21: Mensalidade mínima - Essencial | B21: 320 | C21: R$/mês | D21: Premissa.
A22: Mensalidade mínima - Profissional | B22: 950 | C22: R$/mês | D22: Premissa.
A23: Mensalidade mínima - Premium | B23: 2000 | C23: R$/mês | D23: Premissa.
A24: Implantação (taxa única) - Essencial | B24: 1200 | C24: R$ | D24: Premissa: importação de histórico + treinamento.
A25: Implantação (taxa única) - Profissional | B25: 2800 | C25: R$ | D25: Premissa.
A26: Implantação (taxa única) - Premium | B26: 6000 | C26: R$ | D26: Premissa.
... A29: Licença de consultor/veterinário por mês | B29: 600 | C29: R$/mês | D29: Premissa: painel multi-fazendas.
A30: Crescimento e retenção
A31: Churn mensal de fazendas (cenário base) | B31: 0.012 | C31: % a.m. | D31: Premissa (~13,5% ao ano); meta de retenção do plano de sucesso do cliente.
A32: Custos variáveis e infraestrutura
A33: Infraestrutura por fazenda (banco isolado, app, backup) | B33: 75 | C33: R$/fazenda/mês | D33: Premissa: um banco por fazenda (isolamento) na AWS.
A34: Mensageria (WhatsApp/e-mail/SMS) por fazenda | B34: 30 | C34: R$/fazenda/mês | D34: Premissa.
A35: Infraestrutura fixa (monitoramento, CI/CD, segredos, backup central) | B35: 4000 | C35: R$/mês | D35: Premissa.
A36: Suporte e Sucesso do Cliente (dimensionamento)
A37: Fazendas por atendente N1 | B37: 150 | C37: fazendas | D37: Premissa de capacidade (chat/WhatsApp, 1ª resposta).
A38: Fazendas por gerente de sucesso (CS) | B38: 100 | C38: fazendas | D38: Premissa.
A39: Vacas atendidas por analista zootécnico/vet N2 | B39: 30000 | C39: vacas | D39: Premissa: interpretação de indicadores e protocolos.
A40: Novas fazendas/mês por especialista de implantação | B40: 8 | C40: fazendas/mês | D40: Premissa: ~25 h de implantação por fazenda.
A41: Base de fazendas a partir da qual existe atendente N1 dedicado | B41: 30 | C41: fazendas | D41: Antes disso o N1 é feito por CS e N2 (equipe enxuta no início).
A42: Custo mensal N1 (salário + encargos) | B42: 4500 | C42: R$/mês | D42: Premissa; valores do ano 1, reajustados.
A43: Custo mensal CS | B43: 8000 | C43: R$/mês | D43: Premissa.
A44: Custo mensal analista zootécnico/veterinário N2 | B44: 12000 | C44: R$/mês | D44: Premissa.
A45: Custo mensal especialista de implantação | B45: 7000 | C45: R$/mês | D45: Premissa.
A46: Ferramentas por atendente (helpdesk, chat, telefonia) | B46: 250 | C46: R$/mês | D46: Premissa.
A47: CRM/CS/base de conhecimento por fazenda | B47: 12 | C47: R$/fazenda/mês | D47: Premissa.
A48: Aquisição
A49: Custo variável de aquisição por fazenda (visitas, demonstração, material) | B49: 2500 | C49: R$/fazenda | D49: Premissa.
A50: Comissão de vendas (% do contrato do 1º ano) | B50: 0.08 | C50: % | D50: Premissa.
A51: Conversão de lead qualificado em demonstração | B51: 0.3 | C51: % | D51: Premissa de funil (a validar nos pilotos).
A52: Conversão de demonstração em cliente pagante | B52: 0.25 | C52: % | D52: Premissa de funil.
A53: Mês do ano do evento anual (1-12) | B53: 10 | C53: mês | D53: Premissa.
A54: Cenários (multiplicadores)
A55: Cenário ativo (1 = Conservador, 2 = Base, 3 = Otimista) | B55: 2 | C55: 1/2/3 | D55: ALTERE AQUI para trocar o cenário.
A56: Sensibilidade: fator de preço adicional | B56: 1 | C56: x | D56: Use 1,00 para o caso padrão.
A57: Sensibilidade: fator de churn adicional | B57: 1 | C57: x | D57: Use 1,00 para o caso padrão.
A58: APORTE SOLICITADO (investimento total) | B58: 4700000 | C58: R$ | D58: Decisão da diretoria. Definido a partir da necessidade do caso base + folga.
A59: Aporte - parcela 1: mês | B59: 1 | C59: mês | D59: Liberação por marcos (tranches).
A60: Aporte - parcela 1: % do total | B60: 0.45 | C60: %
A61: Aporte - parcela 2: mês | B61: 10 | C61: mês | D61: Condicionada ao marco: 15 fazendas pagantes.
A62: Aporte - parcela 2: % do total | B62: 0.35 | C62: %
A63: Aporte - parcela 3: mês | B63: 22 | C63: mês | D63: Condicionada ao marco: R$ 1,5 mi de ARR.
A64: Aporte - parcela 3: % do total | B64: =1-t1p-t2p -> 0.2 | C64: % | D64: Calculado: restante.
A65: Tabela de cenários
A66: Multiplicador | B66: Conservador | C66: Base | D66: Otimista | E66: Ativo
A67: Novas fazendas (multiplicador) | B67: 0.6 | C67: 1 | D67: 1.4 | E67: =INDEX(B67:D67,1,scenario) -> 1
A68: Churn (multiplicador) | B68: 1.4 | C68: 1 | D68: 0.7 | E68: =INDEX(B68:D68,1,scenario) -> 1
A69: Preço/ARPA (multiplicador) | B69: 0.95 | C69: 1 | D69: 1 | E69: =INDEX(B69:D69,1,scenario) -> 1
A71: Vetor por ano | B71: Ano 1 | C71: Ano 2 | D71: Ano 3 | E71: Ano 4 | F71: Ano 5 | G71: Unidade | H71: Fonte / observação
A72: Vetores por ano
A73: Novas fazendas por mês (cenário base, após o lançamento) | B73: 3 | C73: 12 | D73: 20 | E73: 26 | F73: 30 | G73: fazendas/mês | H73: Premissa: funil comercial (ver seção de vendas). Ano 1 considera início no mês de lançamento.
A74: Tributos sobre receita (Simples/Presumido + ISS) | B74: 0.06 | C74: 0.08 | D74: 0.13 | E74: 0.14 | F74: 0.14 | G74: % receita | H74: Estimativa: validar com contador (mudança de regime acima de R$ 4,8 mi/ano).
A75: Adoção de módulos premium (% das fazendas) | B75: 0 | C75: 0.1 | D75: 0.18 | E75: 0.25 | F75: 0.3 | G75: % | H75: Premissa.
A76: Adoção do benchmark premium (% das fazendas) | B76: 0 | C76: 0.05 | D76: 0.12 | E76: 0.18 | F76: 0.22 | G76: % | H76: Premissa.
A77: Novas licenças de consultor por mês | B77: 0 | C77: 1 | D77: 2 | E77: 3 | F77: 4 | G77: licenças/mês | H77: Premissa.
A78: Receita do evento anual (ingressos) | B78: 0 | C78: 60000 | D78: 120000 | E78: 200000 | F78: 280000 | G78: R$/ano | H78: Premissa: 150 a 700 participantes x R$ 400.
A79: Custo do evento anual | B79: 0 | C79: 55000 | D79: 90000 | E79: 140000 | F79: 190000 | G79: R$/ano | H79: Premissa.
A80: Patrocínios e convênios (laticínios, nutrição, genética) | B80: 0 | C80: 120000 | D80: 360000 | E80: 600000 | F80: 900000 | G80: R$/ano | H80: Premissa; receita contratada por ano, reconhecida mensalmente.
A81: Marketing fixo (conteúdo, mídia, feiras) | B81: 5000 | C81: 12000 | D81: 20000 | E81: 28000 | F81: 36000 | G81: R$/mês | H81: Premissa.
A82: Despesas gerais e administrativas fixas | B82: 12000 | C82: 16000 | D82: 22000 | E82: 28000 | F82: 34000 | G82: R$/mês | H82: Contabilidade, jurídico, seguros, espaço, ferramentas. Premissa.
A83: Equipe fixa (headcount por ano) - o time de suporte é calculado pelo número de fazendas/vacas
A84: Direção / gestão geral | B84: 1 | C84: 1 | D84: 1 | E84: 1 | F84: 1 | G84: pessoas
A85: Tech lead / arquitetura | B85: 1 | C85: 1 | D85: 1 | E85: 1 | F85: 1 | G85: pessoas
A86: Desenvolvedores | B86: 2 | C86: 3 | D86: 3 | E86: 4 | F86: 5 | G86: pessoas
A87: Dados / IA / benchmark | B87: 0 | C87: 1 | D87: 1 | E87: 1 | F87: 2 | G87: pessoas
A88: Produto / design | B88: 1 | C88: 1 | D88: 1 | E88: 1 | F88: 2 | G88: pessoas
A89: Zootecnia/veterinária (conteúdo, protocolos, benchmark) | B89: 1 | C89: 1 | D89: 1 | E89: 2 | F89: 2 | G89: pessoas
A90: Executivos de vendas | B90: 1 | C90: 2 | D90: 2 | E90: 3 | F90: 3 | G90: pessoas
A91: Marketing / comunidade | B91: 0 | C91: 1 | D91: 1 | E91: 1 | F91: 2 | G91: pessoas
A92: Administrativo / financeiro | B92: 0 | C92: 1 | D92: 1 | E92: 1 | F92: 2 | G92: pessoas
A93: Custo mensal por pessoa (salário + encargos, valores do ano 1)
A94: Direção / gestão geral | B94: 18000 | G94: R$/mês | H94: Premissa.
A95: Tech lead | B95: 22000 | G95: R$/mês | H95: Premissa.
A96: Desenvolvedor | B96: 16000 | G96: R$/mês | H96: Premissa.
A97: Dados / IA | B97: 17000 | G97: R$/mês | H97: Premissa.
A98: Produto / design | B98: 15000 | G98: R$/mês | H98: Premissa.
A99: Zootecnista / veterinário | B99: 12000 | G99: R$/mês | H99: Premissa.
A100: Executivo de vendas (fixo) | B100: 9000 | G100: R$/mês | H100: Premissa (+ comissão).
A101: Marketing / comunidade | B101: 8000 | G101: R$/mês | H101: Premissa.
A102: Administrativo / financeiro | B102: 9000 | G102: R$/mês | H102: Premissa.
A104: Derivados (cálculo)
A105: Mensalidade média - Essencial | B105: =MAX(min_ess,herd_ess*p_ess) -> 360 | C105: R$/mês | D105: MAIOR entre o mínimo e (vacas x preço por vaca)
...

Sheet Anual
A1: DRE, fluxo de caixa, balanço e indicadores (anual)
A3: R$ (exceto onde indicado) | B3: 1 | C3: 2 | D3: 3 | E3: 4 | F3: 5
A4: DEMONSTRAÇÃO DO RESULTADO (DRE)
A5: Assinaturas (por vaca/mês) | B5: =SUMIFS(Mensal!$C$17:$BJ$17,Mensal!$C$6:$BJ$6,B$3) -> 147610.31 | C5: =SUMIFS(Mensal!$C$17:$BJ$17,Mensal!$C$6:$BJ$6,C$3) -> 1467278 | D5: =SUMIFS(Mensal!$C$17:$BJ$17,Mensal!$C$6:$BJ$6,D$3) -> 4329265.2 | E5: =SUMIFS(Mensal!$C$17:$BJ$17,Mensal!$C$6:$BJ$6,E$3) -> 8442476.3 | F5: =SUMIFS(Mensal!$C$17:$BJ$17,Mensal!$C$6:$BJ$6,F$3) -> 13425655
A6: Implantação | B6: =SUMIFS(Mensal!$C$18:$BJ$18,Mensal!$C$6:$BJ$6,B$3) -> 64368 | C6: =SUMIFS(Mensal!$C$18:$BJ$18,Mensal!$C$6:$BJ$6,C$3) -> 360460.8 | D6: =SUMIFS(Mensal!$C$18:$BJ$18,Mensal!$C$6:$BJ$6,D$3) -> 630806.4 | E6: =SUMIFS(Mensal!$C$18:$BJ$18,Mensal!$C$6:$BJ$6,E$3) -> 861050.74 | F6: =SUMIFS(Mensal!$C$18:$BJ$18,Mensal!$C$6:$BJ$6,F$3) -> 1043196.1
A7: Módulos premium | B7: =SUMIFS(Mensal!$C$19:$BJ$19,Mensal!$C$6:$BJ$6,B$3) -> 0 | C7: =SUMIFS(Mensal!$C$19:$BJ$19,Mensal!$C$6:$BJ$6,C$3) -> 41018.154 | D7: =SUMIFS(Mensal!$C$19:$BJ$19,Mensal!$C$6:$BJ$6,D$3) -> 217846.41 | E7: =SUMIFS(Mensal!$C$19:$BJ$19,Mensal!$C$6:$BJ$6,E$3) -> 590029.3 | F7: =SUMIFS(Mensal!$C$19:$BJ$19,Mensal!$C$6:$BJ$6,F$3) -> 1125953.5
A8: Benchmark premium | B8: =SUMIFS(Mensal!$C$20:$BJ$20,Mensal!$C$6:$BJ$6,B$3) -> 0 | C8: =SUMIFS(Mensal!$C$20:$BJ$20,Mensal!$C$6:$BJ$6,C$3) -> 14649.341 | D8: =SUMIFS(Mensal!$C$20:$BJ$20,Mensal!$C$6:$BJ$6,D$3) -> 103736.39 | E8: =SUMIFS(Mensal!$C$20:$BJ$20,Mensal!$C$6:$BJ$6,E$3) -> 303443.64 | F8: =SUMIFS(Mensal!$C$20:$BJ$20,Mensal!$C$6:$BJ$6,F$3) -> 589785.18
A9: Licenças para consultores | B9: =SUMIFS(Mensal!$C$21:$BJ$21,Mensal!$C$6:$BJ$6,B$3) -> 0 | C9: =SUMIFS(Mensal!$C$21:$BJ$21,Mensal!$C$6:$BJ$6,C$3) -> 49140 | D9: =SUMIFS(Mensal!$C$21:$BJ$21,Mensal!$C$6:$BJ$6,D$3) -> 198450 | E9: =SUMIFS(Mensal!$C$21:$BJ$21,Mensal!$C$6:$BJ$6,E$3) -> 462586.95 | F9: =SUMIFS(Mensal!$C$21:$BJ$21,Mensal!$C$6:$BJ$6,F$3) -> 857661.21
A10: Evento anual | B10: =SUMIFS(Mensal!$C$22:$BJ$22,Mensal!$C$6:$BJ$6,B$3) -> 0 | C10: =SUMIFS(Mensal!$C$22:$BJ$22,Mensal!$C$6:$BJ$6,C$3) -> 60000 | D10: =SUMIFS(Mensal!$C$22:$BJ$22,Mensal!$C$6:$BJ$6,D$3) -> 120000 | E10: =SUMIFS(Mensal!$C$22:$BJ$22,Mensal!$C$6:$BJ$6,E$3) -> 200000 | F10: =SUMIFS(Mensal!$C$22:$BJ$22,Mensal!$C$6:$BJ$6,F$3) -> 280000
A11: Patrocínios e convênios | B11: =SUMIFS(Mensal!$C$23:$BJ$23,Mensal!$C$6:$BJ$6,B$3) -> 0 | C11: =SUMIFS(Mensal!$C$23:$BJ$23,Mensal!$C$6:$BJ$6,C$3) -> 120000 | D11: =SUMIFS(Mensal!$C$23:$BJ$23,Mensal!$C$6:$BJ$6,D$3) -> 360000 | E11: =SUMIFS(Mensal!$C$23:$BJ$23,Mensal!$C$6:$BJ$6,E$3) -> 600000 | F11: =SUMIFS(Mensal!$C$23:$BJ$23,Mensal!$C$6:$BJ$6,F$3) -> 900000
A12: Receita bruta | B12: =SUMIFS(Mensal!$C$24:$BJ$24,Mensal!$C$6:$BJ$6,B$3) -> 211978.31 | C12: =SUMIFS(Mensal!$C$24:$BJ$24,Mensal!$C$6:$BJ$6,C$3) -> 2112546.3 | D12: =SUMIFS(Mensal!$C$24:$BJ$24,Mensal!$C$6:$BJ$6,D$3) -> 5960104.4 | E12: =SUMIFS(Mensal!$C$24:$BJ$24,Mensal!$C$6:$BJ$6,E$3) -> 11459587 | F12: =SUMIFS(Mensal!$C$24:$BJ$24,Mensal!$C$6:$BJ$6,F$3) -> 18222251
A13: (-) Tributos sobre a receita | B13: =SUMIFS(Mensal!$C$25:$BJ$25,Mensal!$C$6:$BJ$6,B$3) -> -12718.698 | C13: =SUMIFS(Mensal!$C$25:$BJ$25,Mensal!$C$6:$BJ$6,C$3) -> -169003.7 | D13: =SUMIFS(Mensal!$C$25:$BJ$25,Mensal!$C$6:$BJ$6,D$3) -> -774813.57 | E13: =SUMIFS(Mensal!$C$25:$BJ$25,Mensal!$C$6:$BJ$6,E$3) -> -1604342.2 | F13: =SUMIFS(Mensal!$C$25:$BJ$25,Mensal!$C$6:$BJ$6,F$3) -> -2551115.2
A14: Receita líquida | B14: =SUMIFS(Mensal!$C$26:$BJ$26,Mensal!$C$6:$BJ$6,B$3) -> 199259.61 | C14: =SUMIFS(Mensal!$C$26:$BJ$26,Mensal!$C$6:$BJ$6,C$3) -> 1943542.6 | D14: =SUMIFS(Mensal!$C$26:$BJ$26,Mensal!$C$6:$BJ$6,D$3) -> 5185290.8 | E14: =SUMIFS(Mensal!$C$26:$BJ$26,Mensal!$C$6:$BJ$6,E$3) -> 9855244.8 | F14: =SUMIFS(Mensal!$C$26:$BJ$26,Mensal!$C$6:$BJ$6,F$3) -> 15671136
A15: (-) Infraestrutura variável | B15: =SUMIFS(Mensal!$C$35:$BJ$35,Mensal!$C$6:$BJ$6,B$3) -> -8842.4704 | C15: =SUMIFS(Mensal!$C$35:$BJ$35,Mensal!$C$6:$BJ$6,C$3) -> -87896.045 | D15: =SUMIFS(Mensal!$C$35:$BJ$35,Mensal!$C$6:$BJ$6,D$3) -> -259340.96 | E15: =SUMIFS(Mensal!$C$35:$BJ$35,Mensal!$C$6:$BJ$6,E$3) -> -505739.4 | F15: =SUMIFS(Mensal!$C$35:$BJ$35,Mensal!$C$6:$BJ$6,F$3) -> -804252.51
A16: (-) Mensageria | B16: =SUMIFS(Mensal!$C$36:$BJ$36,Mensal!$C$6:$BJ$6,B$3) -> -3536.9882 | C16: =SUMIFS(Mensal!$C$36:$BJ$36,Mensal!$C$6:$BJ$6,C$3) -> -35158.418 | D16: =SUMIFS(Mensal!$C$36:$BJ$36,Mensal!$C$6:$BJ$6,D$3) -> -103736.39 | E16: =SUMIFS(Mensal!$C$36:$BJ$36,Mensal!$C$6:$BJ$6,E$3) -> -202295.76 | F16: =SUMIFS(Mensal!$C$36:$BJ$36,Mensal!$C$6:$BJ$6,F$3) -> -321701.01
A17: (-) Infraestrutura fixa | B17: =SUMIFS(Mensal!$C$37:$BJ$37,Mensal!$C$6:$BJ$6,B$3) -> -48000 | C17: =SUMIFS(Mensal!$C$37:$BJ$37,Mensal!$C$6:$BJ$6,C$3) -> -50400 | D17: =SUMIFS(Mensal!$C$37:$BJ$37,Mensal!$C$6:$BJ$6,D$3) -> -52920 | E17: =SUMIFS(Mensal!$C$37:$BJ$37,Mensal!$C$6:$BJ$6,E$3) -> -55566 | F17: =SUMIFS(Mensal!$C$37:$BJ$37,Mensal!$C$6:$BJ$6,F$3) -> -58344.3
A18: (-) Equipe de suporte e sucesso | B18: =SUMIFS(Mensal!$C$38:$BJ$38,Mensal!$C$6:$BJ$6,B$3) -> -243000 | C18: =SUMIFS(Mensal!$C$38:$BJ$38,Mensal!$C$6:$BJ$6,C$3) -> -540225 | D18: =SUMIFS(Mensal!$C$38:$BJ$38,Mensal!$C$6:$BJ$6,D$3) -> -1069425 | E18: =SUMIFS(Mensal!$C$38:$BJ$38,Mensal!$C$6:$BJ$6,E$3) -> -1790267.1 | F18: =SUMIFS(Mensal!$C$38:$BJ$38,Mensal!$C$6:$BJ$6,F$3) -> -2510020.4
A19: (-) Ferramentas de suporte | B19: =SUMIFS(Mensal!$C$39:$BJ$39,Mensal!$C$6:$BJ$6,B$3) -> -8164.7953 | C19: =SUMIFS(Mensal!$C$39:$BJ$39,Mensal!$C$6:$BJ$6,C$3) -> -31650.867 | D19: =SUMIFS(Mensal!$C$39:$BJ$39,Mensal!$C$6:$BJ$6,D$3) -> -76223.304 | E19: =SUMIFS(Mensal!$C$39:$BJ$39,Mensal!$C$6:$BJ$6,E$3) -> -138510.15 | F19: =SUMIFS(Mensal!$C$39:$BJ$39,Mensal!$C$6:$BJ$6,F$3) -> -209207.69
A20: Custo dos serviços | B20: =SUMIFS(Mensal!$C$40:$BJ$40,Mensal!$C$6:$BJ$6,B$3) -> -311544.25 | C20: =SUMIFS(Mensal!$C$40:$BJ$40,Mensal!$C$6:$BJ$6,C$3) -> -745330.33 | D20: =SUMIFS(Mensal!$C$40:$BJ$40,Mensal!$C$6:$BJ$6,D$3) -> -1561645.7 | E20: =SUMIFS(Mensal!$C$40:$BJ$40,Mensal!$C$6:$BJ$6,E$3) -> -2692378.4 | F20: =SUMIFS(Mensal!$C$40:$BJ$40,Mensal!$C$6:$BJ$6,F$3) -> -3903525.9
A21: Lucro bruto | B21: =SUMIFS(Mensal!$C$41:$BJ$41,Mensal!$C$6:$BJ$6,B$3) -> -112284.65 | C21: =SUMIFS(Mensal!$C$41:$BJ$41,Mensal!$C$6:$BJ$6,C$3) -> 1198212.2 | D21: =SUMIFS(Mensal!$C$41:$BJ$41,Mensal!$C$6:$BJ$6,D$3) -> 3623645.1 | E21: =SUMIFS(Mensal!$C$41:$BJ$41,Mensal!$C$6:$BJ$6,E$3) -> 7162866.4 | F21: =SUMIFS(Mensal!$C$41:$BJ$41,Mensal!$C$6:$BJ$6,F$3) -> 11767610
A22: Margem bruta (% da receita líquida) | B22: =IFERROR(B21/B14,0) -> -0.56350932 | C22: =IFERROR(C21/C14,0) -> 0.61650939 | D22: =IFERROR(D21/D14,0) -> 0.69883162 | E22: =IFERROR(E21/E14,0) -> 0.72680756 | F22: =IFERROR(F21/F14,0) -> 0.75090983
A23: (-) Equipe fixa (direção, tecnologia, produto, dados, zootecnia, vendas, marketing, administrativo) | B23: =SUMIFS(Mensal!$C$52:$BJ$52,Mensal!$C$6:$BJ$6,B$3) -> -1296000 | C23: =SUMIFS(Mensal!$C$52:$BJ$52,Mensal!$C$6:$BJ$6,C$3) -> -2104200 | D23: =SUMIFS(Mensal!$C$52:$BJ$52,Mensal!$C$6:$BJ$6,D$3) -> -2209410 | E23: =SUMIFS(Mensal!$C$52:$BJ$52,Mensal!$C$6:$BJ$6,E$3) -> -2833866 | F23: =SUMIFS(Mensal!$C$52:$BJ$52,Mensal!$C$6:$BJ$6,F$3) -> -3923654.2
A24: (-) Comissões de vendas | B24: =SUMIFS(Mensal!$C$53:$BJ$53,Mensal!$C$6:$BJ$6,B$3) -> -32451.84 | C24: =SUMIFS(Mensal!$C$53:$BJ$53,Mensal!$C$6:$BJ$6,C$3) -> -181730.3 | D24: =SUMIFS(Mensal!$C$53:$BJ$53,Mensal!$C$6:$BJ$6,D$3) -> -318028.03 | E24: =SUMIFS(Mensal!$C$53:$BJ$53,Mensal!$C$6:$BJ$6,E$3) -> -434108.26 | F24: =SUMIFS(Mensal!$C$53:$BJ$53,Mensal!$C$6:$BJ$6,F$3) -> -525938.86
A25: (-) Aquisição (custo variável) | B25: =SUMIFS(Mensal!$C$54:$BJ$54,Mensal!$C$6:$BJ$6,B$3) -> -67500 | C25: =SUMIFS(Mensal!$C$54:$BJ$54,Mensal!$C$6:$BJ$6,C$3) -> -378000 | D25: =SUMIFS(Mensal!$C$54:$BJ$54,Mensal!$C$6:$BJ$6,D$3) -> -661500 | E25: =SUMIFS(Mensal!$C$54:$BJ$54,Mensal!$C$6:$BJ$6,E$3) -> -902947.5 | F25: =SUMIFS(Mensal!$C$54:$BJ$54,Mensal!$C$6:$BJ$6,F$3) -> -1093955.6
A26: (-) Marketing fixo | B26: =SUMIFS(Mensal!$C$55:$BJ$55,Mensal!$C$6:$BJ$6,B$3) -> -50000 | C26: =SUMIFS(Mensal!$C$55:$BJ$55,Mensal!$C$6:$BJ$6,C$3) -> -151200 | D26: =SUMIFS(Mensal!$C$55:$BJ$55,Mensal!$C$6:$BJ$6,D$3) -> -264600 | E26: =SUMIFS(Mensal!$C$55:$BJ$55,Mensal!$C$6:$BJ$6,E$3) -> -388962 | F26: =SUMIFS(Mensal!$C$55:$BJ$55,Mensal!$C$6:$BJ$6,F$3) -> -525098.7
A27: (-) Custo do evento | B27: =SUMIFS(Mensal!$C$56:$BJ$56,Mensal!$C$6:$BJ$6,B$3) -> 0 | C27: =SUMIFS(Mensal!$C$56:$BJ$56,Mensal!$C$6:$BJ$6,C$3) -> -55000 | D27: =SUMIFS(Mensal!$C$56:$BJ$56,Mensal!$C$6:$BJ$6,D$3) -> -90000 | E27: =SUMIFS(Mensal!$C$56:$BJ$56,Mensal!$C$6:$BJ$6,E$3) -> -140000 | F27: =SUMIFS(Mensal!$C$56:$BJ$56,Mensal!$C$6:$BJ$6,F$3) -> -190000
A28: (-) Gerais e administrativas | B28: =SUMIFS(Mensal!$C$57:$BJ$57,Mensal!$C$6:$BJ$6,B$3) -> -144000 | C28: =SUMIFS(Mensal!$C$57:$BJ$57,Mensal!$C$6:$BJ$6,C$3) -> -201600 | D28: =SUMIFS(Mensal!$C$57:$BJ$57,Mensal!$C$6:$BJ$6,D$3) -> -291060 | E28: =SUMIFS(Mensal!$C$57:$BJ$57,Mensal!$C$6:$BJ$6,E$3) -> -388962 | F28: =SUMIFS(Mensal!$C$57:$BJ$57,Mensal!$C$6:$BJ$6,F$3) -> -495926.55
A29: (-) Itens pontuais | B29: =SUMIFS(Mensal!$C$58:$BJ$58,Mensal!$C$6:$BJ$6,B$3) -> -136000 | C29: =SUMIFS(Mensal!$C$58:$BJ$58,Mensal!$C$6:$BJ$6,C$3) -> -20000 | D29: =SUMIFS(Mensal!$C$58:$BJ$58,Mensal!$C$6:$BJ$6,D$3) -> -20000 | E29: =SUMIFS(Mensal!$C$58:$BJ$58,Mensal!$C$6:$BJ$6,E$3) -> -20000 | F29: =SUMIFS(Mensal!$C$58:$BJ$58,Mensal!$C$6:$BJ$6,F$3) -> -20000
A30: Despesas operacionais | B30: =SUMIFS(Mensal!$C$59:$BJ$59,Mensal!$C$6:$BJ$6,B$3) -> -1725951.8 | C30: =SUMIFS(Mensal!$C$59:$BJ$59,Mensal!$C$6:$BJ$6,C$3) -> -3091730.3 | D30: =SUMIFS(Mensal!$C$59:$BJ$59,Mensal!$C$6:$BJ$6,D$3) -> -3854598 | E30: =SUMIFS(Mensal!$C$59:$BJ$59,Mensal!$C$6:$BJ$6,E$3) -> -5108845.8 | F30: =SUMIFS(Mensal!$C$59:$BJ$59,Mensal!$C$6:$BJ$6,F$3) -> -6774573.9
A31: EBITDA / resultado líquido | B31: =SUMIFS(Mensal!$C$60:$BJ$60,Mensal!$C$6:$BJ$6,B$3) -> -1838236.5 | C31: =SUMIFS(Mensal!$C$60:$BJ$60,Mensal!$C$6:$BJ$6,C$3) -> -1893518.1 | D31: =SUMIFS(Mensal!$C$60:$BJ$60,Mensal!$C$6:$BJ$6,D$3) -> -230952.89 | E31: =SUMIFS(Mensal!$C$60:$BJ$60,Mensal!$C$6:$BJ$6,E$3) -> 2054020.7 | F31: =SUMIFS(Mensal!$C$60:$BJ$60,Mensal!$C$6:$BJ$6,F$3) -> 4993036.3
A32: Margem EBITDA (% da receita líquida) | B32: =IFERROR(B31/B14,0) -> -9.2253343 | C32: =IFERROR(C31/C14,0) -> -0.97426117 | D32: =IFERROR(D31/D14,0) -> -0.044540006 | E32: =IFERROR(E31/E14,0) -> 0.20841904 | F32: =IFERROR(F31/F14,0) -> 0.31861355
A33: FLUXO DE CAIXA
A34: EBITDA | B34: =B31 -> -1838236.5 | C34: =C31 -> -1893518.1 | D34: =D31 -> -230952.89 | E34: =E31 -> 2054020.7 | F34: =F31 -> 4993036.3
A35: Variação do capital de giro | B35: =SUMIFS(Mensal!$C$66:$BJ$66,Mensal!$C$6:$BJ$6,B$3) -> 102001.12 | C35: =SUMIFS(Mensal!$C$66:$BJ$66,Mensal!$C$6:$BJ$6,C$3) -> 39563.951 | D35: =SUMIFS(Mensal!$C$66:$BJ$66,Mensal!$C$6:$BJ$6,D$3) -> -5087.6754 | E35: =SUMIFS(Mensal!$C$66:$BJ$66,Mensal!$C$6:$BJ$6,E$3) -> -4169.7514 | F35: =SUMIFS(Mensal!$C$66:$BJ$66,Mensal!$C$6:$BJ$6,F$3) -> -17092.714
A36: Fluxo de caixa operacional (antes de aportes) | B36: =SUMIFS(Mensal!$C$67:$BJ$67,Mensal!$C$6:$BJ$6,B$3) -> -1736235.4 | C36: =SUMIFS(Mensal!$C$67:$BJ$67,Mensal!$C$6:$BJ$6,C$3) -> -1853954.1 | D36: =SUMIFS(Mensal!$C$67:$BJ$67,Mensal!$C$6:$BJ$6,D$3) -> -236040.56 | E36: =SUMIFS(Mensal!$C$67:$BJ$67,Mensal!$C$6:$BJ$6,E$3) -> 2049850.9 | F36: =SUMIFS(Mensal!$C$67:$BJ$67,Mensal!$C$6:$BJ$6,F$3) -> 4975943.6
A37: Aportes de capital | B37: =SUMIFS(Mensal!$C$69:$BJ$69,Mensal!$C$6:$BJ$6,B$3) -> 3760000 | C37: =SUMIFS(Mensal!$C$69:$BJ$69,Mensal!$C$6:$BJ$6,C$3) -> 940000 | D37: =SUMIFS(Mensal!$C$69:$BJ$69,Mensal!$C$6:$BJ$6,D$3) -> 0 | E37: =SUMIFS(Mensal!$C$69:$BJ$69,Mensal!$C$6:$BJ$6,E$3) -> 0 | F37: =SUMIFS(Mensal!$C$69:$BJ$69,Mensal!$C$6:$BJ$6,F$3) -> 0
A38: Variação líquida de caixa | B38: =B36+B37 -> 2023764.6 | C38: =C36+C37 -> -913954.11 | D38: =D36+D37 -> -236040.56 | E38: =E36+E37 -> 2049850.9 | F38: =F36+F37 -> 4975943.6
A39: Caixa final (com aportes) | B39: =INDEX(Mensal!$C$70:$BJ$70,1,12*B$3) -> 2023764.6 | C39: =INDEX(Mensal!$C$70:$BJ$70,1,12*C$3) -> 1109810.5 | D39: =INDEX(Mensal!$C$70:$BJ$70,1,12*D$3) -> 873769.96 | E39: =INDEX(Mensal!$C$70:$BJ$70,1,12*E$3) -> 2923620.9 | F39: =INDEX(Mensal!$C$70:$BJ$70,1,12*F$3) -> 7899564.4
A40: Caixa acumulado antes de aportes | B40: =INDEX(Mensal!$C$68:$BJ$68,1,12*B$3) -> -1736235.4 | C40: =INDEX(Mensal!$C$68:$BJ$68,1,12*C$3) -> -3590189.5 | D40: =INDEX(Mensal!$C$68:$BJ$68,1,12*D$3) -> -3826230 | E40: =INDEX(Mensal!$C$68:$BJ$68,1,12*E$3) -> -1776379.1 | F40: =INDEX(Mensal!$C$68:$BJ$68,1,12*F$3) -> 3199564.4
A41: BALANÇO PROJETADO (fim do ano)
A42: Caixa | B42: =B39 -> 2023764.6 | C42: =C39 -> 1109810.5 | D42: =D39 -> 873769.96 | E42: =E39 -> 2923620.9 | F42: =F39 -> 7899564.4
A43: Contas a receber | B43: =INDEX(Mensal!$C$64:$BJ$64,1,12*B$3) -> 11804.184 | C43: =INDEX(Mensal!$C$64:$BJ$64,1,12*C$3) -> 78206.144 | D43: =INDEX(Mensal!$C$64:$BJ$64,1,12*D$3) -> 182560.1 | E43: =INDEX(Mensal!$C$64:$BJ$64,1,12*E$3) -> 322515.95 | F43: =INDEX(Mensal!$C$64:$BJ$64,1,12*F$3) -> 489707.1
A44: ATIVO TOTAL | B44: =B42+B43 -> 2035568.8 | C44: =C42+C43 -> 1188016.7 | D44: =D42+D43 -> 1056330.1 | E44: =E42+E43 -> 3246136.8 | F44: =F42+F43 -> 8389271.5
A45: Contas a pagar (fornecedores e encargos) | B45: =INDEX(Mensal!$C$65:$BJ$65,1,12*B$3) -> 113805.3 | C45: =INDEX(Mensal!$C$65:$BJ$65,1,12*C$3) -> 219771.21 | D45: =INDEX(Mensal!$C$65:$BJ$65,1,12*D$3) -> 319037.49 | E45: =INDEX(Mensal!$C$65:$BJ$65,1,12*E$3) -> 454823.59 | F45: =INDEX(Mensal!$C$65:$BJ$65,1,12*F$3) -> 604922.03
A46: Capital integralizado (aportes acumulados) | B46: =SUMIFS(Mensal!$C$69:$BJ$69,Mensal!$C$5:$BJ$5,"<="&12*B$3) -> 3760000 | C46: =SUMIFS(Mensal!$C$69:$BJ$69,Mensal!$C$5:$BJ$5,"<="&12*C$3) -> 4700000 | D46: =SUMIFS(Mensal!$C$69:$BJ$69,Mensal!$C$5:$BJ$5,"<="&12*D$3) -> 4700000 | E46: =SUMIFS(Mensal!$C$69:$BJ$69,Mensal!$C$5:$BJ$5,"<="&12*E$3) -> 4700000 | F46: =SUMIFS(Mensal!$C$69:$BJ$69,Mensal!$C$5:$BJ$5,"<="&12*F$3) -> 4700000
A47: Lucros (prejuízos) acumulados | B47: =SUMIFS(Mensal!$C$60:$BJ$60,Mensal!$C$5:$BJ$5,"<="&12*B$3) -> -1838236.5 | C47: =SUMIFS(Mensal!$C$60:$BJ$60,Mensal!$C$5:$BJ$5,"<="&12*C$3) -> -3731754.5 | D47: =SUMIFS(Mensal!$C$60:$BJ$60,Mensal!$C$5:$BJ$5,"<="&12*D$3) -> -3962707.4 | E47: =SUMIFS(Mensal!$C$60:$BJ$60,Mensal!$C$5:$BJ$5,"<="&12*E$3) -> -1908686.8 | F47: =SUMIFS(Mensal!$C$60:$BJ$60,Mensal!$C$5:$BJ$5,"<="&12*F$3) -> 3084349.5
A48: Patrimônio líquido | B48: =B46+B47 -> 1921763.5 | C48: =C46+C47 -> 968245.45 | D48: =D46+D47 -> 737292.56 | E48: =E46+E47 -> 2791313.2 | F48: =F46+F47 -> 7784349.5
A49: PASSIVO + PATRIMÔNIO LÍQUIDO | B49: =B45+B48 -> 2035568.8 | C49: =C45+C48 -> 1188016.7 | D49: =D45+D48 -> 1056330.1 | E49: =E45+E48 -> 3246136.8 | F49: =F45+F48 -> 8389271.5
A50: Conferência (ativo - passivo - PL; deve ser 0) | B50: =ROUND(B44-B49,0) -> 0 | C50: =ROUND(C44-C49,0) -> 0 | D50: =ROUND(D44-D49,0) -> 0 | E50: =ROUND(E44-E49,0) -> 0 | F50: =ROUND(F44-F49,0) -> 0
A51: INDICADORES
A52: Fazendas ativas (fim do ano) | B52: =INDEX(Mensal!$C$11:$BJ$11,1,12*B$3) -> 25.739643 | C52: =INDEX(Mensal!$C$11:$BJ$11,1,12*C$3) -> 157.13433 | D52: =INDEX(Mensal!$C$11:$BJ$11,1,12*D$3) -> 360.71905 | E52: =INDEX(Mensal!$C$11:$BJ$11,1,12*E$3) -> 604.28015 | F52: =INDEX(Mensal!$C$11:$BJ$11,1,12*F$3) -> 859.94847
A53: Novas fazendas no ano | B53: =SUMIFS(Mensal!$C$9:$BJ$9,Mensal!$C$6:$BJ$6,B$3) -> 27 | C53: =SUMIFS(Mensal!$C$9:$BJ$9,Mensal!$C$6:$BJ$6,C$3) -> 144 | D53: =SUMIFS(Mensal!$C$9:$BJ$9,Mensal!$C$6:$BJ$6,D$3) -> 240 | E53: =SUMIFS(Mensal!$C$9:$BJ$9,Mensal!$C$6:$BJ$6,E$3) -> 312 | F53: =SUMIFS(Mensal!$C$9:$BJ$9,Mensal!$C$6:$BJ$6,F$3) -> 360
A54: Fazendas perdidas no ano | B54: =SUMIFS(Mensal!$C$10:$BJ$10,Mensal!$C$6:$BJ$6,B$3) -> 1.2603574 | C54: =SUMIFS(Mensal!$C$10:$BJ$10,Mensal!$C$6:$BJ$6,C$3) -> 12.605315 | D54: =SUMIFS(Mensal!$C$10:$BJ$10,Mensal!$C$6:$BJ$6,D$3) -> 36.415276 | E54: =SUMIFS(Mensal!$C$10:$BJ$10,Mensal!$C$6:$BJ$6,E$3) -> 68.438906 | F54: =SUMIFS(Mensal!$C$10:$BJ$10,Mensal!$C$6:$BJ$6,F$3) -> 104.33168
A55: Vacas em lactação atendidas (fim do ano) | B55: =INDEX(Mensal!$C$13:$BJ$13,1,12*B$3) -> 4375.7392 | C55: =INDEX(Mensal!$C$13:$BJ$13,1,12*C$3) -> 26712.836 | D55: =INDEX(Mensal!$C$13:$BJ$13,1,12*D$3) -> 61322.239 | E55: =INDEX(Mensal!$C$13:$BJ$13,1,12*E$3) -> 102727.62 | F55: =INDEX(Mensal!$C$13:$BJ$13,1,12*F$3) -> 146191.24
A56: Licenças de consultor (fim do ano) | B56: =INDEX(Mensal!$C$14:$BJ$14,1,12*B$3) -> 0 | C56: =INDEX(Mensal!$C$14:$BJ$14,1,12*C$3) -> 12 | D56: =INDEX(Mensal!$C$14:$BJ$14,1,12*D$3) -> 36 | E56: =INDEX(Mensal!$C$14:$BJ$14,1,12*E$3) -> 72 | F56: =INDEX(Mensal!$C$14:$BJ$14,1,12*F$3) -> 120
A57: Mensalidade média por fazenda (dez) | B57: =INDEX(Mensal!$C$15:$BJ$15,1,12*B$3) -> 1252 | C57: =INDEX(Mensal!$C$15:$BJ$15,1,12*C$3) -> 1314.6 | D57: =INDEX(Mensal!$C$15:$BJ$15,1,12*D$3) -> 1380.33 | E57: =INDEX(Mensal!$C$15:$BJ$15,1,12*E$3) -> 1449.3465 | F57: =INDEX(Mensal!$C$15:$BJ$15,1,12*F$3) -> 1521.8138
A58: ARR - receita recorrente anualizada (dez x 12) | B58: =INDEX(Mensal!$C$27:$BJ$27,1,12*B$3)*12 -> 366251.13 | C58: =INDEX(Mensal!$C$27:$BJ$27,1,12*C$3)*12 -> 2699779.6 | D58: =INDEX(Mensal!$C$27:$BJ$27,1,12*D$3)*12 -> 6923404.6 | E58: =INDEX(Mensal!$C$27:$BJ$27,1,12*E$3)*12 -> 12639617 | F58: =INDEX(Mensal!$C$27:$BJ$27,1,12*F$3)*12 -> 19456171
A59: Churn anual de fazendas (efetivo) | B59: =1-(1-churn_m*f_churn*s_churn)^12 -> 0.13486609 | C59: =1-(1-churn_m*f_churn*s_churn)^12 -> 0.13486609 | D59: =1-(1-churn_m*f_churn*s_churn)^12 -> 0.13486609 | E59: =1-(1-churn_m*f_churn*s_churn)^12 -> 0.13486609 | F59: =1-(1-churn_m*f_churn*s_churn)^12 -> 0.13486609
A60: Headcount fixo (fim do ano) | B60: =INDEX(Mensal!$C$61:$BJ$61,1,12*B$3) -> 7 | C60: =INDEX(Mensal!$C$61:$BJ$61,1,12*C$3) -> 12 | D60: =INDEX(Mensal!$C$61:$BJ$61,1,12*D$3) -> 12 | E60: =INDEX(Mensal!$C$61:$BJ$61,1,12*E$3) -> 15 | F60: =INDEX(Mensal!$C$61:$BJ$61,1,12*F$3) -> 20
A61: Headcount de suporte e sucesso (fim do ano) | B61: =INDEX(Mensal!$C$33:$BJ$33,1,12*B$3) -> 3 | C61: =INDEX(Mensal!$C$33:$BJ$33,1,12*C$3) -> 7 | D61: =INDEX(Mensal!$C$33:$BJ$33,1,12*D$3) -> 13 | E61: =INDEX(Mensal!$C$33:$BJ$33,1,12*E$3) -> 20 | F61: =INDEX(Mensal!$C$33:$BJ$33,1,12*F$3) -> 24
A62: Headcount total (fim do ano) | B62: =INDEX(Mensal!$C$62:$BJ$62,1,12*B$3) -> 10 | C62: =INDEX(Mensal!$C$62:$BJ$62,1,12*C$3) -> 19 | D62: =INDEX(Mensal!$C$62:$BJ$62,1,12*D$3) -> 25 | E62: =INDEX(Mensal!$C$62:$BJ$62,1,12*E$3) -> 35 | F62: =INDEX(Mensal!$C$62:$BJ$62,1,12*F$3) -> 44
A63: Custo de suporte e sucesso (equipe + ferramentas) | B63: =-(B18+B19) -> 251164.8 | C63: =-(C18+C19) -> 571875.87 | D63: =-(D18+D19) -> 1145648.3 | E63: =-(E18+E19) -> 1928777.2 | F63: =-(F18+F19) -> 2719228.1
A64: Fazendas-mês faturadas | B64: =SUMIFS(Mensal!$C$12:$BJ$12,Mensal!$C$6:$BJ$6,B$3) -> 117.89961 | C64: =SUMIFS(Mensal!$C$12:$BJ$12,Mensal!$C$6:$BJ$6,C$3) -> 1116.1403 | D64: =SUMIFS(Mensal!$C$12:$BJ$12,Mensal!$C$6:$BJ$6,D$3) -> 3136.3987 | E64: =SUMIFS(Mensal!$C$12:$BJ$12,Mensal!$C$6:$BJ$6,E$3) -> 5825.0227 | F64: =SUMIFS(Mensal!$C$12:$BJ$12,Mensal!$C$6:$BJ$6,F$3) -> 8822.1404
A65: Custo de suporte por fazenda/mês | B65: =IFERROR(B63/B64,0) -> 2130.3277 | C65: =IFERROR(C63/C64,0) -> 512.36918 | D65: =IFERROR(D63/D64,0) -> 365.27509 | E65: =IFERROR(E63/E64,0) -> 331.11926 | F65: =IFERROR(F63/F64,0) -> 308.2277
A66: Custo de suporte por vaca/mês | B66: =IFERROR(B65/herd_avg,0) -> 12.531339 | C66: =IFERROR(C65/herd_avg,0) -> 3.0139364 | D66: =IFERROR(D65/herd_avg,0) -> 2.148677 | E66: =IFERROR(E65/herd_avg,0) -> 1.9477603 | F66: =IFERROR(F65/herd_avg,0) -> 1.8131041
A67: Custo de suporte (% da receita líquida) | B67: =IFERROR(B63/B14,0) -> 1.2604903 | C67: =IFERROR(C63/C14,0) -> 0.29424407 | D67: =IFERROR(D63/D14,0) -> 0.22094196 | E67: =IFERROR(E63/E14,0) -> 0.19571074 | F67: =IFERROR(F63/F14,0) -> 0.17351825
A68: ARPA de assinatura do ano (R$/fazenda/mês) | B68: =IFERROR(B5/B64,0) -> 1252 | C68: =IFERROR(C5/C64,0) -> 1314.6 | D68: =IFERROR(D5/D64,0) -> 1380.33 | E68: =IFERROR(E5/E64,0) -> 1449.3465 | F68: =IFERROR(F5/F64,0) -> 1521.8138
A69: Custo variável por fazenda/mês (infra, mensageria, suporte, ferramentas) | B69: =IFERROR(-(B15+B16+B18+B19)/B64,0) -> 2235.3277 | C69: =IFERROR(-(C15+C16+C18+C19)/C64,0) -> 622.61918 | D69: =IFERROR(-(D15+D16+D18+D19)/D64,0) -> 481.03759 | E69: =IFERROR(-(E15+E16+E18+E19)/E64,0) -> 452.66988 | F69: =IFERROR(-(F15+F16+F18+F19)/F64,0) -> 435.85586
A70: Contribuição por fazenda/mês | B70: =B68-B69 -> -983.3277 | C70: =C68-C69 -> 691.98082 | D70: =D68-D69 -> 899.29241 | E70: =E68-E69 -> 996.67662 | F70: =F68-F69 -> 1085.958
A71: CAC combinado (vendas, comissão, aquisição e marketing / novas fazendas) | B71: =IFERROR(-(SUMIFS(Mensal!$C$49:$BJ$49,Mensal!$C$6:$BJ$6,B$3)+B24+B25+B26)/B53,0) -> 9553.7719 | C71: =IFERROR(-(SUMIFS(Mensal!$C$49:$BJ$49,Mensal!$C$6:$BJ$6,C$3)+C24+C25+C26)/C53,0) -> 6512.016 | D71: =IFERROR(-(SUMIFS(Mensal!$C$49:$BJ$49,Mensal!$C$6:$BJ$6,D$3)+D24+D25+D26)/D53,0) -> 6176.1168 | E71: =IFERROR(-(SUMIFS(Mensal!$C$49:$BJ$49,Mensal!$C$6:$BJ$6,E$3)+E24+E25+E26)/E53,0) -> 6734.2573 | F71: =IFERROR(-(SUMIFS(Mensal!$C$49:$BJ$49,Mensal!$C$6:$BJ$6,F$3)+F24+F25+F26)/F53,0) -> 7052.27
A72: LTV (contribuição / churn mensal) | B72: =IFERROR(B70/(churn_m*f_churn*s_churn),0) -> -81943.975 | C72: =IFERROR(C70/(churn_m*f_churn*s_churn),0) -> 57665.068 | D72: =IFERROR(D70/(churn_m*f_churn*s_churn),0) -> 74941.034 | E72: =IFERROR(E70/(churn_m*f_churn*s_churn),0) -> 83056.385 | F72: =IFERROR(F70/(churn_m*f_churn*s_churn),0) -> 90496.497
A73: LTV / CAC | B73: =IFERROR(B72/B71,0) -> -8.5771334 | C73: =IFERROR(C72/C71,0) -> 8.8551791 | D73: =IFERROR(D72/D71,0) -> 12.134005 | E73: =IFERROR(E72/E71,0) -> 12.333414 | F73: =IFERROR(F72/F71,0) -> 12.832251
A74: Payback do CAC (meses) | B74: =IFERROR(B71/B70,0) -> -9.7157558 | C74: =IFERROR(C71/C70,0) -> 9.4106886 | D74: =IFERROR(D71/D70,0) -> 6.8677515 | E74: =IFERROR(E71/E70,0) -> 6.7567124 | F74: =IFERROR(F71/F70,0) -> 6.4940543
A75: Demonstrações necessárias no ano (novas fazendas / conversão) | B75: =IFERROR(B53/conv2,0) -> 108 | C75: =IFERROR(C53/conv2,0) -> 576 | D75: =IFERROR(D53/conv2,0) -> 960 | E75: =IFERROR(E53/conv2,0) -> 1248 | F75: =IFERROR(F53/conv2,0) -> 1440
A76: Leads qualificados necessários no ano | B76: =IFERROR(B75/conv1,0) -> 360 | C76: =IFERROR(C75/conv1,0) -> 1920 | D76: =IFERROR(D75/conv1,0) -> 3200 | E76: =IFERROR(E75/conv1,0) -> 4160 | F76: =IFERROR(F75/conv1,0) -> 4800
A77: Receita líquida por vaca atendida/ano (média) | B77: =IFERROR(B14/(B64*herd_avg/12),0) -> 119.29967 | C77: =IFERROR(C14/(C64*herd_avg/12),0) -> 122.91577 | D77: =IFERROR(D14/(D64*herd_avg/12),0) -> 116.70089 | E77: =IFERROR(E14/(E64*herd_avg/12),0) -> 119.42689 | F77: =IFERROR(F14/(F64*herd_avg/12),0) -> 125.38883

Sheet Retornos
A1: Retornos, break-even, necessidade de caixa e investimento por fase
A3: Indicador | B3: Valor | C3: Observação
A4: Necessidade máxima de caixa (queima acumulada antes de aportes) | B4: =-MIN(Mensal!$C$68:$BJ$68) -> 4044057.4 | C4: Pico negativo do caixa acumulado.
A5: Aporte solicitado | B5: =ask -> 4700000 | C5: Premissa (decisão da diretoria).
A6: Folga do aporte sobre a necessidade | B6: =IFERROR(ask/B4-1,0) -> 0.16219912 | C6: Colchão para atrasos de vendas.
A7: Caixa mínimo com aportes | B7: =MIN(Mensal!$C$70:$BJ$70) -> 489402.22 | C7: Negativo = falta de caixa neste cenário.
A8: Mês do ponto mínimo (antes de aportes) | B8: =MATCH(MIN(Mensal!$C$68:$BJ$68),Mensal!$C$68:$BJ$68,0) -> 31
A9: Break-even operacional (1º mês com EBITDA positivo) | B9: =IFERROR(MATCH(1,Mensal!$C$71:$BJ$71,0),"> 60") -> 32 | C9: Mês do plano.
A10: Payback do investimento (caixa acumulado volta a zero) | B10: =IFERROR(MATCH(1,Mensal!$C$72:$BJ$72,0),"> 60") -> 54 | C10: Mês do plano; "> 60" = não ocorre em 5 anos.
A12: Fluxo de caixa livre (antes de aportes) | B12: Ano 1 | C12: Ano 2 | D12: Ano 3 | E12: Ano 4 | F12: Ano 5
A13: Fluxo operacional do ano | B13: =Anual!B36 -> -1736235.4 | C13: =Anual!C36 -> -1853954.1 | D13: =Anual!D36 -> -236040.56 | E13: =Anual!E36 -> 2049850.9 | F13: =Anual!F36 -> 4975943.6
A14: (+) Valor residual no ano 5 (múltiplo x receita líquida) | B14: 0 | C14: 0 | D14: 0 | E14: 0 | F14: =tv_mult*Anual!F14 -> 23506704
A15: Fluxo com valor residual | B15: =B13+B14 -> -1736235.4 | C15: =C13+C14 -> -1853954.1 | D15: =D13+D14 -> -236040.56 | E15: =E13+E14 -> 2049850.9 | F15: =F13+F14 -> 28482648
A17: VPL sem valor residual (a TMA) | B17: =NPV(disc,B13:F13) -> -226235.57 | C17: Desconto anual, fluxos no fim de cada ano.
A18: VPL com valor residual (a TMA) | B18: =NPV(disc,B15:F15) -> 7476441.2
A19: TIR sem valor residual | B19: =IFERROR(IRR(B13:F13),"n/d") -> 0.21547458 | C19: "n/d" = fluxos sem inversão de sinal.
A20: TIR com valor residual | B20: =IFERROR(IRR(B15:F15),"n/d") -> 0.84007865
A22: Investimento (consumo de caixa) por fase | B22: Mês inicial | C22: Mês final | D22: Consumo(-)/geração(+) de caixa | E22: Fazendas ao fim da fase | F22: ARR ao fim da fase
A23: Fase 1 - Fundação e pilotos (M1-M6) | B23: 1 | C23: 6 | D23: =SUMIFS(Mensal!$C$67:$BJ$67,Mensal!$C$5:$BJ$5,">="&B23,Mensal!$C$5:$BJ$5,"<="&C23) -> -829857.18 | E23: =INDEX(Mensal!$C$11:$BJ$11,1,C23) -> 8.892432 | F23: =INDEX(Mensal!$C$27:$BJ$27,1,C23)*12 -> 111601.52
A24: Fase 2 - Lançamento comercial (M7-M18) | B24: 7 | C24: 18 | D24: =SUMIFS(Mensal!$C$67:$BJ$67,Mensal!$C$5:$BJ$5,">="&B24,Mensal!$C$5:$BJ$5,"<="&C24) -> -2001899 | E24: =INDEX(Mensal!$C$11:$BJ$11,1,C24) -> 93.815355 | F24: =INDEX(Mensal!$C$27:$BJ$27,1,C24)*12 -> 1611357.6
A25: Fase 3 - Escala regional (M19-M36) | B25: 19 | C25: 36 | D25: =SUMIFS(Mensal!$C$67:$BJ$67,Mensal!$C$5:$BJ$5,">="&B25,Mensal!$C$5:$BJ$5,"<="&C25) -> -994473.9 | E25: =INDEX(Mensal!$C$11:$BJ$11,1,C25) -> 360.71905 | F25: =INDEX(Mensal!$C$27:$BJ$27,1,C25)*12 -> 6923404.6
A26: Fase 4 - Expansão e plataforma (M37-M60) | B26: 37 | C26: 60 | D26: =SUMIFS(Mensal!$C$67:$BJ$67,Mensal!$C$5:$BJ$5,">="&B26,Mensal!$C$5:$BJ$5,"<="&C26) -> 7025794.5 | E26: =INDEX(Mensal!$C$11:$BJ$11,1,C26) -> 859.94847 | F26: =INDEX(Mensal!$C$27:$BJ$27,1,C26)*12 -> 19456171
A27: Total | D27: =SUM(D23:D26) -> 3199564.4

Sheet Suporte
A1: Suporte e Sucesso do Cliente: dimensionamento por fazendas e vacas
A2: Valores do ano 1 (sem reajuste). Edite as fazendas em azul; a equipe, o custo e a margem escalam por fórmula usando as razões da aba Premissas.
A4: Dimensionamento (mensal) | B4: Cenário A | C4: Cenário B | D4: Cenário C | E4: Cenário D | F4: Cenário E | G4: Cenário F
A5: Fazendas ativas | B5: 25 | C5: 50 | D5: 100 | E5: 200 | F5: 400 | G5: 800
A6: Vacas atendidas | B6: =B5*herd_avg -> 4250 | C6: =C5*herd_avg -> 8500 | D6: =D5*herd_avg -> 17000 | E6: =E5*herd_avg -> 34000 | F6: =F5*herd_avg -> 68000 | G6: =G5*herd_avg -> 136000
A7: Novas fazendas por mês (premissa: 5% da base) | B7: =B5*0.05 -> 1.25 | C7: =C5*0.05 -> 2.5 | D7: =D5*0.05 -> 5 | E7: =E5*0.05 -> 10 | F7: =F5*0.05 -> 20 | G7: =G5*0.05 -> 40
A8: Atendentes N1 | B8: =IF(B5<n1_from,0,ROUNDUP(B5/r_n1,0)) -> 0 | C8: =IF(C5<n1_from,0,ROUNDUP(C5/r_n1,0)) -> 1 | D8: =IF(D5<n1_from,0,ROUNDUP(D5/r_n1,0)) -> 1 | E8: =IF(E5<n1_from,0,ROUNDUP(E5/r_n1,0)) -> 2 | F8: =IF(F5<n1_from,0,ROUNDUP(F5/r_n1,0)) -> 3 | G8: =IF(G5<n1_from,0,ROUNDUP(G5/r_n1,0)) -> 6
A9: Gerentes de sucesso (CS) | B9: =MAX(1,ROUNDUP(B5/r_cs,0)) -> 1 | C9: =MAX(1,ROUNDUP(C5/r_cs,0)) -> 1 | D9: =MAX(1,ROUNDUP(D5/r_cs,0)) -> 1 | E9: =MAX(1,ROUNDUP(E5/r_cs,0)) -> 2 | F9: =MAX(1,ROUNDUP(F5/r_cs,0)) -> 4 | G9: =MAX(1,ROUNDUP(G5/r_cs,0)) -> 8
A10: Analistas zootécnicos/vet N2 | B10: =ROUNDUP(B6/r_n2,0) -> 1 | C10: =ROUNDUP(C6/r_n2,0) -> 1 | D10: =ROUNDUP(D6/r_n2,0) -> 1 | E10: =ROUNDUP(E6/r_n2,0) -> 2 | F10: =ROUNDUP(F6/r_n2,0) -> 3 | G10: =ROUNDUP(G6/r_n2,0) -> 5
A11: Especialistas de implantação | B11: =ROUNDUP(B7/r_onb,0) -> 1 | C11: =ROUNDUP(C7/r_onb,0) -> 1 | D11: =ROUNDUP(D7/r_onb,0) -> 1 | E11: =ROUNDUP(E7/r_onb,0) -> 2 | F11: =ROUNDUP(F7/r_onb,0) -> 3 | G11: =ROUNDUP(G7/r_onb,0) -> 5
A12: Total de pessoas em suporte e sucesso | B12: =SUM(B8:B11) -> 3 | C12: =SUM(C8:C11) -> 4 | D12: =SUM(D8:D11) -> 4 | E12: =SUM(E8:E11) -> 8 | F12: =SUM(F8:F11) -> 13 | G12: =SUM(G8:G11) -> 24
A13: Custo da equipe | B13: =B8*c_n1+B9*c_cs+B10*c_n2+B11*c_onb -> 27000 | C13: =C8*c_n1+C9*c_cs+C10*c_n2+C11*c_onb -> 31500 | D13: =D8*c_n1+D9*c_cs+D10*c_n2+D11*c_onb -> 31500 | E13: =E8*c_n1+E9*c_cs+E10*c_n2+E11*c_onb -> 63000 | F13: =F8*c_n1+F9*c_cs+F10*c_n2+F11*c_onb -> 102500 | G13: =G8*c_n1+G9*c_cs+G10*c_n2+G11*c_onb -> 186000
A14: Custo de ferramentas | B14: =B12*tool_seat+B5*tool_farm -> 1050 | C14: =C12*tool_seat+C5*tool_farm -> 1600 | D14: =D12*tool_seat+D5*tool_farm -> 2200 | E14: =E12*tool_seat+E5*tool_farm -> 4400 | F14: =F12*tool_seat+F5*tool_farm -> 8050 | G14: =G12*tool_seat+G5*tool_farm -> 15600
A15: Infra e mensageria por fazenda (variável) | B15: =B5*(infra_var+msg) -> 2625 | C15: =C5*(infra_var+msg) -> 5250 | D15: =D5*(infra_var+msg) -> 10500 | E15: =E5*(infra_var+msg) -> 21000 | F15: =F5*(infra_var+msg) -> 42000 | G15: =G5*(infra_var+msg) -> 84000
A16: Custo total de suporte, sucesso e operação por cliente | B16: =B13+B14+B15 -> 30675 | C16: =C13+C14+C15 -> 38350 | D16: =D13+D14+D15 -> 44200 | E16: =E13+E14+E15 -> 88400 | F16: =F13+F14+F15 -> 152550 | G16: =G13+G14+G15 -> 285600
A17: Custo por fazenda/mês | B17: =B16/B5 -> 1227 | C17: =C16/C5 -> 767 | D17: =D16/D5 -> 442 | E17: =E16/E5 -> 442 | F17: =F16/F5 -> 381.375 | G17: =G16/G5 -> 357
A18: Custo por vaca/mês | B18: =B16/B6 -> 7.2176471 | C18: =C16/C6 -> 4.5117647 | D18: =D16/D6 -> 2.6 | E18: =E16/E6 -> 2.6 | F18: =F16/F6 -> 2.2433824 | G18: =G16/G6 -> 2.1
A19: Receita de assinatura por fazenda/mês (ARPA) | B19: =arpa_base -> 1252 | C19: =arpa_base -> 1252 | D19: =arpa_base -> 1252 | E19: =arpa_base -> 1252 | F19: =arpa_base -> 1252 | G19: =arpa_base -> 1252
A20: Custo de suporte e operação (% da assinatura) | B20: =B17/B19 -> 0.98003195 | C20: =C17/C19 -> 0.61261981 | D20: =D17/D19 -> 0.35303514 | E20: =E17/E19 -> 0.35303514 | F20: =F17/F19 -> 0.30461262 | G20: =G17/G19 -> 0.28514377
A21: Fazendas por pessoa de suporte e sucesso | B21: =B5/B12 -> 8.3333333 | C21: =C5/C12 -> 12.5 | D21: =D5/D12 -> 25 | E21: =E5/E12 -> 25 | F21: =F5/F12 -> 30.769231 | G21: =G5/G12 -> 33.333333
A23: Nota: a linha "Custo total ... por cliente" inclui N1, CS, N2, implantação, ferramentas, infraestrutura e mensageria; as despesas de N3 (engenharia) estão no time de desenvolvimento.
A25: SLAs POR PLANO (horário de atendimento e prazos)
A26: Item | B26: Essencial | C26: Profissional | D26: Premium
A27: Canais | B27: Chat no app, e-mail, base de conhecimento | C27: + WhatsApp | D27: + telefone e WhatsApp prioritário, gerente de sucesso dedicado
A28: Horário de atendimento | B28: Seg-Sex 8h-18h | C28: Seg-Sáb 6h-19h | D28: Seg-Sáb 6h-20h + plantão P1 24x7
A29: P1 Crítica (sistema fora do ar / dados incorretos): 1ª resposta | B29: 4 h úteis | C29: 1 h | D29: 30 min (24x7)
A30: P1 Crítica: meta de resolução | B30: 24 h | C30: 8 h | D30: 4 h
A31: P2 Alta (função principal degradada, importação falha): 1ª resposta | B31: 8 h úteis | C31: 4 h | D31: 2 h
A32: P2 Alta: meta de resolução | B32: 3 dias úteis | C32: 2 dias úteis | D32: 1 dia útil
A33: P3 Média (dúvida de uso, falha com contorno): 1ª resposta | B33: 1 dia útil | C33: 8 h | D33: 4 h
A34: P3 Média: meta de resolução | B34: 5 dias úteis | C34: 3 dias úteis | D34: 2 dias úteis
A35: P4 Baixa (sugestão, melhoria): 1ª resposta | B35: 2 dias úteis | C35: 1 dia útil | D35: 8 h
A36: Revisão de resultados com CS | B36: Trimestral (coletiva) | C36: Trimestral (individual) | D36: Mensal (individual)
A37: Apoio zootécnico/veterinário (N2) | B37: Sob demanda, via e-mail | C37: 2 consultas/mês | D37: Ilimitado + revisão mensal de protocolo
A38: Disponibilidade-alvo da plataforma | B38: 99,5% | C38: 99,7% | D38: 99,9%

Sheet Cenários e sensibilidade
A1: Cenários e sensibilidade (valores gerados pelo modelo)
A2: Valores colados a partir de execuções do modelo com o seletor de cenário (1/2/3) e fatores de sensibilidade. Mesmo aporte solicitado em todos os cenários. Reexecute para atualizar após mudar premissas.
A4: Indicador | B4: Conservador | C4: Base | D4: Otimista
A5: Fazendas ativas (fim do ano 3) | B5: 205.84354 | C5: 360.71905 | D5: 524.76415
A6: Fazendas ativas (fim do ano 5) | B6: 473.59393 | C6: 859.94847 | D6: 1286.9562
A7: Vacas atendidas (ano 5) | B7: 80510.968 | C7: 146191.24 | D7: 218782.55
A8: ARR (ano 3, R$) | B8: 4064441.7 | C8: 6923404.6 | D8: 9771924.9
A9: ARR (ano 5, R$) | B9: 11171156 | C9: 19456171 | D9: 28131848
A10: Receita líquida ano 3 (R$) | B10: 3123872.1 | C10: 5185290.8 | D10: 7205416.9
A11: Receita líquida ano 5 (R$) | B11: 9177855.6 | C11: 15671136 | D11: 22358941
A12: EBITDA ano 3 (R$) | B12: -1350001.4 | C12: -230952.89 | D12: 815463.27
A13: EBITDA ano 5 (R$) | B13: 696490.66 | C13: 4993036.3 | D13: 9225814
A14: Margem EBITDA ano 5 | B14: 0.075888169 | C14: 0.31861355 | D14: 0.41262304
A15: Margem bruta ano 5 | B15: 0.74171232 | C15: 0.75090983 | D15: 0.74459457
A16: Necessidade máxima de caixa (R$) | B16: 5696925.5 | C16: 4044057.4 | D16: 3423971.7
... A19: Break-even operacional (mês) | B19: 44 | C19: 32 | D19: 28
A20: Payback do investimento (mês) | B20: > 60 | C20: 54 | D20: 45
A21: VPL sem valor residual (R$) | B21: -3377012.5 | C21: -226235.57 | D21: 2848667.4
A22: VPL com valor residual (R$) | B22: 1134087.1 | C22: 7476441.2 | D22: 13838534
A23: TIR sem valor residual | B23: n/d | C23: 0.21547458 | D23: 0.61685394
A24: TIR com valor residual | B24: 0.36246121 | C24: 0.84007865 | D24: 1.1911935
A25: Headcount total (ano 5) | B25: 35 | C25: 44 | D25: 56
A28: Sensibilidade: VPL com valor residual (R$) - preço x churn
A29: Fator de preço \ fator de churn | B29: churn x0.7 | C29: churn x1.0 | D29: churn x1.4
A30: preço x0.8 | B30: 4847715.1 | C30: 4257051.8 | D30: 3512759.3
A31: preço x0.9 | B31: 6536253.6 | C31: 5866746.5 | D31: 5026600.4
A32: preço x1.0 | B32: 8224792.1 | C32: 7476441.2 | D32: 6540441.6
A33: preço x1.1 | B33: 9913330.6 | C33: 9086136 | D33: 8054282.7
A34: preço x1.2 | B34: 11601869 | C34: 10695831 | D34: 9568123.9
A37: Sensibilidade: EBITDA do ano 5 (R$) - preço x churn
A38: Fator de preço \ fator de churn | B38: churn x0.7 | C38: churn x1.0 | D38: churn x1.4
A39: preço x0.8 | B39: 3053741.9 | C39: 2609581.6 | D39: 2037692.7
A40: preço x0.9 | B40: 4316423.4 | C40: 3801309 | D40: 3143985.6
A41: preço x1.0 | B41: 5579104.9 | C41: 4993036.3 | D41: 4250278.5
A42: preço x1.1 | B42: 6841786.4 | C42: 6184763.6 | D42: 5356571.4
A43: preço x1.2 | B43: 8104467.9 | C43: 7376491 | D43: 6462864.3
A46: Sensibilidade: necessidade máxima de caixa (R$) - preço x churn
A47: Fator de preço \ fator de churn | B47: churn x0.7 | C47: churn x1.0 | D47: churn x1.4
A48: preço x0.8 | B48: 4895481.2 | C48: 5007153 | D48: 5192295.4
A49: preço x0.9 | B49: 4382093.4 | C49: 4434279.1 | D49: 4537803.6
A50: preço x1.0 | B50: 3990017.3 | C50: 4044057.4 | D50: 4139421.4
A51: preço x1.1 | B51: 3653596.9 | C51: 3700857.5 | D51: 3792674.7
A52: preço x1.2 | B52: 3376421.7 | C52: 3414302.1 | D52: 3491116.4
A55: Sensibilidade: volume de novas fazendas (base = 1,0)
A56: Fator de novas fazendas | B56: Fazendas (ano 5) | C56: EBITDA ano 5 | D56: Necessidade de caixa | E56: Break-even (mês)
A57: x0.6 | B57: 515.96908 | C57: 1468441.9 | D57: 5232569.3 | E57: 43
A58: x0.8 | B58: 687.95878 | C58: 3278599.6 | D58: 4488996.5 | E58: 34
A59: x1.0 | B59: 859.94847 | C59: 4993036.3 | D59: 4044057.4 | E59: 32
A60: x1.2 | B60: 1031.9382 | C60: 6672527.1 | D60: 3642030.3 | E60: 29
A61: x1.4 | B61: 1203.9279 | C61: 8376935.8 | D61: 3462031 | E61: 29

Sheet Mensal
A1: Motor mensal (somente fórmulas)
A3: Linha | B3: Unid. | C3: M1 | D3: M2 | E3: M3 | F3: M4 | G3: M5 | H3: M6 | I3: M7 | J3: M8 | K3: M9 | L3: M10 | M3: M11 | N3: M12 | O3: M13 | P3: M14 | Q3: M15 | R3: M16 | S3: M17 | T3: M18 | U3: M19 | V3: M20 | W3: M21 | X3: M22 | Y3: M23 | Z3: M24 | AA3: M25 | AB3: M26 | AC3: M27 | AD3: M28 | AE3: M29 | AF3: M30 | AG3: M31 | AH3: M32 | AI3: M33 | AJ3: M34 | AK3: M35 | AL3: M36 | AM3: M37 | AN3: M38 | AO3: M39 | AP3: M40 | AQ3: M41 | AR3: M42 | AS3: M43 | AT3: M44 | AU3: M45 | AV3: M46 | AW3: M47 | AX3: M48 | AY3: M49 | AZ3: M50 | BA3: M51 | BB3: M52 | BC3: M53 | BD3: M54 | BE3: M55 | BF3: M56 | BG3: M57 | BH3: M58 | BI3: M59 | BJ3: M60
A4: Linha do tempo
A5: Mês | B5: # | C5: 1 | D5: =C5+1 -> 2 | E5: =D5+1 -> 3 | F5: =E5+1 -> 4 | G5: =F5+1 -> 5 | H5: =G5+1 -> 6 | I5: =H5+1 -> 7 | J5: =I5+1 -> 8 | K5: =J5+1 -> 9 | ... BJ5: =BI5+1 -> 60
A6: Ano | B6: # | C6: =ROUNDUP(C5/12,0) -> 1 | D6: =ROUNDUP(D5/12,0) -> 1 | E6: =ROUNDUP(E5/12,0) -> 1 | F6: =ROUNDUP(F5/12,0) -> 1 | G6: =ROUNDUP(G5/12,0) -> 1 | H6: =ROUNDUP(H5/12,0) -> 1 | I6: =ROUNDUP(I5/12,0) -> 1 | J6: =ROUNDUP(J5/12,0) -> 1 | ... BJ6: =ROUNDUP(BJ5/12,0) -> 5
A7: Fator de reajuste (IPCA) | B7: x | C7: =(1+reajuste)^(C6-1) -> 1 | D7: =(1+reajuste)^(D6-1) -> 1 | E7: =(1+reajuste)^(E6-1) -> 1 | F7: =(1+reajuste)^(F6-1) -> 1 | G7: =(1+reajuste)^(G6-1) -> 1 | H7: =(1+reajuste)^(H6-1) -> 1 | I7: =(1+reajuste)^(I6-1) -> 1 | J7: =(1+reajuste)^(J6-1) -> 1 | ... BJ7: =(1+reajuste)^(BJ6-1) -> 1.2155063
A8: Clientes (fazendas e vacas)
A9: Novas fazendas | B9: fazendas | C9: =IF(C5<launch_month,0,INDEX(new_farms_y,1,C6)*f_new) -> 0 | D9: =IF(D5<launch_month,0,INDEX(new_farms_y,1,D6)*f_new) -> 0 | E9: =IF(E5<launch_month,0,INDEX(new_farms_y,1,E6)*f_new) -> 0 | F9: =IF(F5<launch_month,0,INDEX(new_farms_y,1,F6)*f_new) -> 3 | G9: =IF(G5<launch_month,0,INDEX(new_farms_y,1,G6)*f_new) -> 3 | H9: =IF(H5<launch_month,0,INDEX(new_farms_y,1,H6)*f_new) -> 3 | I9: =IF(I5<launch_month,0,INDEX(new_farms_y,1,I6)*f_new) -> 3 | J9: =IF(J5<launch_month,0,INDEX(new_farms_y,1,J6)*f_new) -> 3 | ... BJ9: =IF(BJ5<launch_month,0,INDEX(new_farms_y,1,BJ6)*f_new) -> 30
A10: Fazendas perdidas (churn) | B10: fazendas | C10: =0 -> 0 | D10: =C11*churn_m*f_churn*s_churn -> 0 | E10: =D11*churn_m*f_churn*s_churn -> 0 | F10: =E11*churn_m*f_churn*s_churn -> 0 | G10: =F11*churn_m*f_churn*s_churn -> 0.036 | H10: =G11*churn_m*f_churn*s_churn -> 0.071568 | I10: =H11*churn_m*f_churn*s_churn -> 0.10670918 | J10: =I11*churn_m*f_churn*s_churn -> 0.14142867 | K10: =J11*churn_m*f_churn*s_churn -> 0.17573153 | ... BJ10: =BI11*churn_m*f_churn*s_churn -> 10.080346
A11: Fazendas ativas (fim do mês) | B11: fazendas | C11: =C9-C10 -> 0 | D11: =C11+D9-D10 -> 0 | E11: =D11+E9-E10 -> 0 | F11: =E11+F9-F10 -> 3 | G11: =F11+G9-G10 -> 5.964 | H11: =G11+H9-H10 -> 8.892432 | I11: =H11+I9-I10 -> 11.785723 | J11: =I11+J9-J10 -> 14.644294 | K11: =J11+K9-K10 -> 17.468563 | ... BJ11: =BI11+BJ9-BJ10 -> 859.94847
A12: Fazendas ativas (média do mês) | B12: fazendas | C12: =C11/2 -> 0 | D12: =(C11+D11)/2 -> 0 | E12: =(D11+E11)/2 -> 0 | F12: =(E11+F11)/2 -> 1.5 | G12: =(F11+G11)/2 -> 4.482 | H12: =(G11+H11)/2 -> 7.428216 | I12: =(H11+I11)/2 -> 10.339077 | J12: =(I11+J11)/2 -> 13.215008 | K12: =(J11+K11)/2 -> 16.056428 | ... BJ12: =(BI11+BJ11)/2 -> 849.98864
A13: Vacas em lactação atendidas (fim do mês) | B13: vacas | C13: =C11*herd_avg -> 0 | D13: =D11*herd_avg -> 0 | E13: =E11*herd_avg -> 0 | F13: =F11*herd_avg -> 510 | G13: =G11*herd_avg -> 1013.88 | H13: =H11*herd_avg -> 1511.7134 | I13: =I11*herd_avg -> 2003.5729 | J13: =J11*herd_avg -> 2489.53 | ... BJ13: =BJ11*herd_avg -> 146191.24
A14: Licenças de consultor ativas | B14: licenças | C14: =IF(C5<=12,0,INDEX(new_cons_y,1,C6)) -> 0 | D14: =C14+IF(D5<=12,0,INDEX(new_cons_y,1,D6)) -> 0 | E14: =D14+IF(E5<=12,0,INDEX(new_cons_y,1,E6)) -> 0 | F14: =E14+IF(F5<=12,0,INDEX(new_cons_y,1,F6)) -> 0 | G14: =F14+IF(G5<=12,0,INDEX(new_cons_y,1,G6)) -> 0 | H14: =G14+IF(H5<=12,0,INDEX(new_cons_y,1,H6)) -> 0 | I14: =H14+IF(I5<=12,0,INDEX(new_cons_y,1,I6)) -> 0 | J14: =I14+IF(J5<=12,0,INDEX(new_cons_y,1,J6)) -> 0 | K14: =J14+IF(K5<=12,0,INDEX(new_cons_y,1,K6)) -> 0 | ... BJ14: =BI14+IF(BJ5<=12,0,INDEX(new_cons_y,1,BJ6)) -> 120
A15: Mensalidade média por fazenda (com reajuste e cenário) | B15: R$ | C15: =arpa_base*C7*f_price*s_price -> 1252 | D15: =arpa_base*D7*f_price*s_price -> 1252 | E15: =arpa_base*E7*f_price*s_price -> 1252 | F15: =arpa_base*F7*f_price*s_price -> 1252 | G15: =arpa_base*G7*f_price*s_price -> 1252 | H15: =arpa_base*H7*f_price*s_price -> 1252 | I15: =arpa_base*I7*f_price*s_price -> 1252 | J15: =arpa_base*J7*f_price*s_price -> 1252 | ... BJ15: =arpa_base*BJ7*f_price*s_price -> 1521.8138
A16: Receita bruta
A17: Assinatura (por vaca/mês, com mínimo por plano) | B17: R$ | C17: =C12*C15 -> 0 | D17: =D12*D15 -> 0 | E17: =E12*E15 -> 0 | F17: =F12*F15 -> 1878 | G17: =G12*G15 -> 5611.464 | H17: =H12*H15 -> 9300.1264 | I17: =I12*I15 -> 12944.525 | J17: =J12*J15 -> 16545.191 | ... BJ17: =BJ12*BJ15 -> 1293524.5
A18: Implantação (taxa única) | B18: R$ | C18: =C9*setup_avg*C7*f_price*s_price -> 0 | D18: =D9*setup_avg*D7*f_price*s_price -> 0 | E18: =E9*setup_avg*E7*f_price*s_price -> 0 | F18: =F9*setup_avg*F7*f_price*s_price -> 7152 | G18: =G9*setup_avg*G7*f_price*s_price -> 7152 | H18: =H9*setup_avg*H7*f_price*s_price -> 7152 | I18: =I9*setup_avg*I7*f_price*s_price -> 7152 | J18: =J9*setup_avg*J7*f_price*s_price -> 7152 | ... BJ18: =BJ9*setup_avg*BJ7*f_price*s_price -> 86933.007
A19: Módulos premium | B19: R$ | C19: =C12*INDEX(adopt_mod_y,1,C6)*price_mod*C7 -> 0 | D19: =D12*INDEX(adopt_mod_y,1,D6)*price_mod*D7 -> 0 | E19: =E12*INDEX(adopt_mod_y,1,E6)*price_mod*E7 -> 0 | F19: =F12*INDEX(adopt_mod_y,1,F6)*price_mod*F7 -> 0 | G19: =G12*INDEX(adopt_mod_y,1,G6)*price_mod*G7 -> 0 | H19: =H12*INDEX(adopt_mod_y,1,H6)*price_mod*H7 -> 0 | I19: =I12*INDEX(adopt_mod_y,1,I6)*price_mod*I7 -> 0 | J19: =J12*INDEX(adopt_mod_y,1,J6)*price_mod*J7 -> 0 | ... BJ19: =BJ12*INDEX(adopt_mod_y,1,BJ6)*price_mod*BJ7 -> 108482.48
A20: Benchmark premium | B20: R$ | C20: =C12*INDEX(adopt_bench_y,1,C6)*price_bench*C7 -> 0 | D20: =D12*INDEX(adopt_bench_y,1,D6)*price_bench*D7 -> 0 | E20: =E12*INDEX(adopt_bench_y,1,E6)*price_bench*E7 -> 0 | F20: =F12*INDEX(adopt_bench_y,1,F6)*price_bench*F7 -> 0 | G20: =G12*INDEX(adopt_bench_y,1,G6)*price_bench*G7 -> 0 | H20: =H12*INDEX(adopt_bench_y,1,H6)*price_bench*H7 -> 0 | I20: =I12*INDEX(adopt_bench_y,1,I6)*price_bench*I7 -> 0 | J20: =J12*INDEX(adopt_bench_y,1,J6)*price_bench*J7 -> 0 | ... BJ20: =BJ12*INDEX(adopt_bench_y,1,BJ6)*price_bench*BJ7 -> 56824.158
A21: Licenças para consultores | B21: R$ | C21: =C14*price_cons*C7 -> 0 | D21: =D14*price_cons*D7 -> 0 | E21: =E14*price_cons*E7 -> 0 | F21: =F14*price_cons*F7 -> 0 | G21: =G14*price_cons*G7 -> 0 | H21: =H14*price_cons*H7 -> 0 | I21: =I14*price_cons*I7 -> 0 | J21: =J14*price_cons*J7 -> 0 | ... BJ21: =BJ14*price_cons*BJ7 -> 87516.45
A22: Evento anual (ingressos) | B22: R$ | C22: =IF(MOD(C5-1,12)+1=event_month,INDEX(event_rev_y,1,C6),0) -> 0 | D22: =IF(MOD(D5-1,12)+1=event_month,INDEX(event_rev_y,1,D6),0) -> 0 | E22: =IF(MOD(E5-1,12)+1=event_month,INDEX(event_rev_y,1,E6),0) -> 0 | F22: =IF(MOD(F5-1,12)+1=event_month,INDEX(event_rev_y,1,F6),0) -> 0 | G22: =IF(MOD(G5-1,12)+1=event_month,INDEX(event_rev_y,1,G6),0) -> 0 | H22: =IF(MOD(H5-1,12)+1=event_month,INDEX(event_rev_y,1,H6),0) -> 0 | I22: =IF(MOD(I5-1,12)+1=event_month,INDEX(event_rev_y,1,I6),0) -> 0 | J22: =IF(MOD(J5-1,12)+1=event_month,INDEX(event_rev_y,1,J6),0) -> 0 | ... BJ22: =IF(MOD(BJ5-1,12)+1=event_month,INDEX(event_rev_y,1,BJ6),0) -> 0
A23: Patrocínios e convênios | B23: R$ | C23: =INDEX(spons_y,1,C6)/12*IF(C5>=launch_month,1,0) -> 0 | D23: =INDEX(spons_y,1,D6)/12*IF(D5>=launch_month,1,0) -> 0 | E23: =INDEX(spons_y,1,E6)/12*IF(E5>=launch_month,1,0) -> 0 | F23: =INDEX(spons_y,1,F6)/12*IF(F5>=launch_month,1,0) -> 0 | G23: =INDEX(spons_y,1,G6)/12*IF(G5>=launch_month,1,0) -> 0 | H23: =INDEX(spons_y,1,H6)/12*IF(H5>=launch_month,1,0) -> 0 | I23: =INDEX(spons_y,1,I6)/12*IF(I5>=launch_month,1,0) -> 0 | J23: =INDEX(spons_y,1,J6)/12*IF(J5>=launch_month,1,0) -> 0 | ... BJ23: =INDEX(spons_y,1,BJ6)/12*IF(BJ5>=launch_month,1,0) -> 75000
A24: RECEITA BRUTA | B24: R$ | C24: =SUM(C17:C23) -> 0 | D24: =SUM(D17:D23) -> 0 | E24: =SUM(E17:E23) -> 0 | F24: =SUM(F17:F23) -> 9030 | G24: =SUM(G17:G23) -> 12763.464 | H24: =SUM(H17:H23) -> 16452.126 | I24: =SUM(I17:I23) -> 20096.525 | J24: =SUM(J17:J23) -> 23697.191 | ... BJ24: =SUM(BJ17:BJ23) -> 1708280.6
A25: (-) Tributos sobre a receita | B25: R$ | C25: =-C24*INDEX(tax_y,1,C6) -> 0 | D25: =-D24*INDEX(tax_y,1,D6) -> 0 | E25: =-E24*INDEX(tax_y,1,E6) -> 0 | F25: =-F24*INDEX(tax_y,1,F6) -> -541.8 | G25: =-G24*INDEX(tax_y,1,G6) -> -765.80784 | H25: =-H24*INDEX(tax_y,1,H6) -> -987.12759 | I25: =-I24*INDEX(tax_y,1,I6) -> -1205.7915 | J25: =-J24*INDEX(tax_y,1,J6) -> -1421.8314 | ... BJ25: =-BJ24*INDEX(tax_y,1,BJ6) -> -239159.28
A26: RECEITA LÍQUIDA | B26: R$ | C26: =C24+C25 -> 0 | D26: =D24+D25 -> 0 | E26: =E24+E25 -> 0 | F26: =F24+F25 -> 8488.2 | G26: =G24+G25 -> 11997.656 | H26: =H24+H25 -> 15464.999 | I26: =I24+I25 -> 18890.733 | J26: =J24+J25 -> 22275.359 | ... BJ26: =BJ24+BJ25 -> 1469121.3
A27: Memo: receita recorrente do mês (assinatura + módulos + benchmark + consultores + patrocínios) | B27: R$ | C27: =C17+C19+C20+C21+C23 -> 0 | D27: =D17+D19+D20+D21+D23 -> 0 | E27: =E17+E19+E20+E21+E23 -> 0 | F27: =F17+F19+F20+F21+F23 -> 1878 | G27: =G17+G19+G20+G21+G23 -> 5611.464 | H27: =H17+H19+H20+H21+H23 -> 9300.1264 | I27: =I17+I19+I20+I21+I23 -> 12944.525 | J27: =J17+J19+J20+J21+J23 -> 16545.191 | ... BJ27: =BJ17+BJ19+BJ20+BJ21+BJ23 -> 1621347.6
A28: Equipe de suporte e sucesso (dimensionada por fazendas e vacas)
A29: Atendentes N1 | B29: pessoas | C29: =IF(OR(C5<launch_month,C11<n1_from),0,ROUNDUP(C11/r_n1,0)) -> 0 | D29: =IF(OR(D5<launch_month,D11<n1_from),0,ROUNDUP(D11/r_n1,0)) -> 0 | E29: =IF(OR(E5<launch_month,E11<n1_from),0,ROUNDUP(E11/r_n1,0)) -> 0 | F29: =IF(OR(F5<launch_month,F11<n1_from),0,ROUNDUP(F11/r_n1,0)) -> 0 | G29: =IF(OR(G5<launch_month,G11<n1_from),0,ROUNDUP(G11/r_n1,0)) -> 0 | H29: =IF(OR(H5<launch_month,H11<n1_from),0,ROUNDUP(H11/r_n1,0)) -> 0 | I29: =IF(OR(I5<launch_month,I11<n1_from),0,ROUNDUP(I11/r_n1,0)) -> 0 | J29: =IF(OR(J5<launch_month,J11<n1_from),0,ROUNDUP(J11/r_n1,0)) -> 0 | ... BJ29: =IF(OR(BJ5<launch_month,BJ11<n1_from),0,ROUNDUP(BJ11/r_n1,0)) -> 6
A30: Gerentes de sucesso (CS) | B30: pessoas | C30: =IF(C5<launch_month,0,MAX(1,ROUNDUP(C11/r_cs,0))) -> 0 | D30: =IF(D5<launch_month,0,MAX(1,ROUNDUP(D11/r_cs,0))) -> 0 | E30: =IF(E5<launch_month,0,MAX(1,ROUNDUP(E11/r_cs,0))) -> 0 | F30: =IF(F5<launch_month,0,MAX(1,ROUNDUP(F11/r_cs,0))) -> 1 | G30: =IF(G5<launch_month,0,MAX(1,ROUNDUP(G11/r_cs,0))) -> 1 | H30: =IF(H5<launch_month,0,MAX(1,ROUNDUP(H11/r_cs,0))) -> 1 | I30: =IF(I5<launch_month,0,MAX(1,ROUNDUP(I11/r_cs,0))) -> 1 | J30: =IF(J5<launch_month,0,MAX(1,ROUNDUP(J11/r_cs,0))) -> 1 | ... BJ30: =IF(BJ5<launch_month,0,MAX(1,ROUNDUP(BJ11/r_cs,0))) -> 9
A31: Analistas zootécnicos/veterinários N2 | B31: pessoas | C31: =IF(C5<launch_month,0,ROUNDUP(C13/r_n2,0)) -> 0 | D31: =IF(D5<launch_month,0,ROUNDUP(D13/r_n2,0)) -> 0 | E31: =IF(E5<launch_month,0,ROUNDUP(E13/r_n2,0)) -> 0 | F31: =IF(F5<launch_month,0,ROUNDUP(F13/r_n2,0)) -> 1 | G31: =IF(G5<launch_month,0,ROUNDUP(G13/r_n2,0)) -> 1 | H31: =IF(H5<launch_month,0,ROUNDUP(H13/r_n2,0)) -> 1 | I31: =IF(I5<launch_month,0,ROUNDUP(I13/r_n2,0)) -> 1 | J31: =IF(J5<launch_month,0,ROUNDUP(J13/r_n2,0)) -> 1 | ... BJ31: =IF(BJ5<launch_month,0,ROUNDUP(BJ13/r_n2,0)) -> 5
A32: Especialistas de implantação | B32: pessoas | C32: =IF(C5<launch_month,0,ROUNDUP(C9/r_onb,0)) -> 0 | D32: =IF(D5<launch_month,0,ROUNDUP(D9/r_onb,0)) -> 0 | E32: =IF(E5<launch_month,0,ROUNDUP(E9/r_onb,0)) -> 0 | F32: =IF(F5<launch_month,0,ROUNDUP(F9/r_onb,0)) -> 1 | G32: =IF(G5<launch_month,0,ROUNDUP(G9/r_onb,0)) -> 1 | H32: =IF(H5<launch_month,0,ROUNDUP(H9/r_onb,0)) -> 1 | I32: =IF(I5<launch_month,0,ROUNDUP(I9/r_onb,0)) -> 1 | J32: =IF(J5<launch_month,0,ROUNDUP(J9/r_onb,0)) -> 1 | ... BJ32: =IF(BJ5<launch_month,0,ROUNDUP(BJ9/r_onb,0)) -> 4
A33: Total da equipe de suporte e sucesso | B33: pessoas | C33: =C29+C30+C31+C32 -> 0 | D33: =D29+D30+D31+D32 -> 0 | E33: =E29+E30+E31+E32 -> 0 | F33: =F29+F30+F31+F32 -> 3 | G33: =G29+G30+G31+G32 -> 3 | H33: =H29+H30+H31+H32 -> 3 | I33: =I29+I30+I31+I32 -> 3 | J33: =J29+J30+J31+J32 -> 3 | ... BJ33: =BJ29+BJ30+BJ31+BJ32 -> 24
A34: Custo dos serviços (COGS)
A35: Infraestrutura variável (por fazenda) | B35: R$ | C35: =-C12*infra_var*C7 -> 0 | D35: =-D12*infra_var*D7 -> 0 | E35: =-E12*infra_var*E7 -> 0 | F35: =-F12*infra_var*F7 -> -112.5 | G35: =-G12*infra_var*G7 -> -336.15 | H35: =-H12*infra_var*H7 -> -557.1162 | I35: =-I12*infra_var*I7 -> -775.43081 | J35: =-J12*infra_var*J7 -> -991.12564 | ... BJ35: =-BJ12*infra_var*BJ7 -> -77487.488
A36: Mensageria | B36: R$ | C36: =-C12*msg*C7 -> 0 | D36: =-D12*msg*D7 -> 0 | E36: =-E12*msg*E7 -> 0 | F36: =-F12*msg*F7 -> -45 | G36: =-G12*msg*G7 -> -134.46 | H36: =-H12*msg*H7 -> -222.84648 | I36: =-I12*msg*I7 -> -310.17232 | J36: =-J12*msg*J7 -> -396.45025 | ... BJ36: =-BJ12*msg*BJ7 -> -30994.995
A37: Infraestrutura fixa | B37: R$ | C37: =-infra_fix*C7 -> -4000 | D37: =-infra_fix*D7 -> -4000 | E37: =-infra_fix*E7 -> -4000 | F37: =-infra_fix*F7 -> -4000 | G37: =-infra_fix*G7 -> -4000 | H37: =-infra_fix*H7 -> -4000 | I37: =-infra_fix*I7 -> -4000 | J37: =-infra_fix*J7 -> -4000 | ... BJ37: =-infra_fix*BJ7 -> -4862.025
A38: Equipe de suporte e sucesso (N1, CS, N2, implantação) | B38: R$ | C38: =-(C29*c_n1+C30*c_cs+C31*c_n2+C32*c_onb)*C7 -> 0 | D38: =-(D29*c_n1+D30*c_cs+D31*c_n2+D32*c_onb)*D7 -> 0 | E38: =-(E29*c_n1+E30*c_cs+E31*c_n2+E32*c_onb)*E7 -> 0 | F38: =-(F29*c_n1+F30*c_cs+F31*c_n2+F32*c_onb)*F7 -> -27000 | G38: =-(G29*c_n1+G30*c_cs+G31*c_n2+G32*c_onb)*G7 -> -27000 | H38: =-(H29*c_n1+H30*c_cs+H31*c_n2+H32*c_onb)*H7 -> -27000 | I38: =-(I29*c_n1+I30*c_cs+I31*c_n2+I32*c_onb)*I7 -> -27000 | J38: =-(J29*c_n1+J30*c_cs+J31*c_n2+J32*c_onb)*J7 -> -27000 | ... BJ38: =-(BJ29*c_n1+BJ30*c_cs+BJ31*c_n2+BJ32*c_onb)*BJ7 -> -227299.67
A39: Ferramentas de suporte (helpdesk, CRM, base de conhecimento) | B39: R$ | C39: =-(C33*tool_seat+C12*tool_farm)*C7 -> 0 | D39: =-(D33*tool_seat+D12*tool_farm)*D7 -> 0 | E39: =-(E33*tool_seat+E12*tool_farm)*E7 -> 0 | F39: =-(F33*tool_seat+F12*tool_farm)*F7 -> -768 | G39: =-(G33*tool_seat+G12*tool_farm)*G7 -> -803.784 | H39: =-(H33*tool_seat+H12*tool_farm)*H7 -> -839.13859 | I39: =-(I33*tool_seat+I12*tool_farm)*I7 -> -874.06893 | J39: =-(J33*tool_seat+J12*tool_farm)*J7 -> -908.5801 | ... BJ39: =-(BJ33*tool_seat+BJ12*tool_farm)*BJ7 -> -19691.036
A40: CUSTO DOS SERVIÇOS | B40: R$ | C40: =SUM(C35:C39) -> -4000 | D40: =SUM(D35:D39) -> -4000 | E40: =SUM(E35:E39) -> -4000 | F40: =SUM(F35:F39) -> -31925.5 | G40: =SUM(G35:G39) -> -32274.394 | H40: =SUM(H35:H39) -> -32619.101 | I40: =SUM(I35:I39) -> -32959.672 | J40: =SUM(J35:J39) -> -33296.156 | ... BJ40: =SUM(BJ35:BJ39) -> -360335.21
A41: LUCRO BRUTO | B41: R$ | C41: =C26+C40 -> -4000 | D41: =D26+D40 -> -4000 | E41: =E26+E40 -> -4000 | F41: =F26+F40 -> -23437.3 | G41: =G26+G40 -> -20276.738 | H41: =H26+H40 -> -17154.102 | I41: =I26+I40 -> -14068.939 | J41: =J26+J40 -> -11020.797 | ... BJ41: =BJ26+BJ40 -> 1108786.1
A42: Despesas operacionais
A43: Equipe: Direção / gestão geral | B43: R$ | C43: =-INDEX(hc_dir,1,C6)*cc_dir*C7 -> -18000 | D43: =-INDEX(hc_dir,1,D6)*cc_dir*D7 -> -18000 | E43: =-INDEX(hc_dir,1,E6)*cc_dir*E7 -> -18000 | F43: =-INDEX(hc_dir,1,F6)*cc_dir*F7 -> -18000 | G43: =-INDEX(hc_dir,1,G6)*cc_dir*G7 -> -18000 | H43: =-INDEX(hc_dir,1,H6)*cc_dir*H7 -> -18000 | I43: =-INDEX(hc_dir,1,I6)*cc_dir*I7 -> -18000 | J43: =-INDEX(hc_dir,1,J6)*cc_dir*J7 -> -18000 | ... BJ43: =-INDEX(hc_dir,1,BJ6)*cc_dir*BJ7 -> -21879.112
A44: Equipe: Tech lead | B44: R$ | C44: =-INDEX(hc_tl,1,C6)*cc_tl*C7 -> -22000 | D44: =-INDEX(hc_tl,1,D6)*cc_tl*D7 -> -22000 | E44: =-INDEX(hc_tl,1,E6)*cc_tl*E7 -> -22000 | F44: =-INDEX(hc_tl,1,F6)*cc_tl*F7 -> -22000 | G44: =-INDEX(hc_tl,1,G6)*cc_tl*G7 -> -22000 | H44: =-INDEX(hc_tl,1,H6)*cc_tl*H7 -> -22000 | I44: =-INDEX(hc_tl,1,I6)*cc_tl*I7 -> -22000 | J44: =-INDEX(hc_tl,1,J6)*cc_tl*J7 -> -22000 | ... BJ44: =-INDEX(hc_tl,1,BJ6)*cc_tl*BJ7 -> -26741.138
A45: Equipe: Desenvolvimento | B45: R$ | C45: =-INDEX(hc_dev,1,C6)*cc_dev*C7 -> -32000 | D45: =-INDEX(hc_dev,1,D6)*cc_dev*D7 -> -32000 | E45: =-INDEX(hc_dev,1,E6)*cc_dev*E7 -> -32000 | F45: =-INDEX(hc_dev,1,F6)*cc_dev*F7 -> -32000 | G45: =-INDEX(hc_dev,1,G6)*cc_dev*G7 -> -32000 | H45: =-INDEX(hc_dev,1,H6)*cc_dev*H7 -> -32000 | I45: =-INDEX(hc_dev,1,I6)*cc_dev*I7 -> -32000 | J45: =-INDEX(hc_dev,1,J6)*cc_dev*J7 -> -32000 | ... BJ45: =-INDEX(hc_dev,1,BJ6)*cc_dev*BJ7 -> -97240.5
A46: Equipe: Dados / IA | B46: R$ | C46: =-INDEX(hc_data,1,C6)*cc_data*C7 -> 0 | D46: =-INDEX(hc_data,1,D6)*cc_data*D7 -> 0 | E46: =-INDEX(hc_data,1,E6)*cc_data*E7 -> 0 | F46: =-INDEX(hc_data,1,F6)*cc_data*F7 -> 0 | G46: =-INDEX(hc_data,1,G6)*cc_data*G7 -> 0 | H46: =-INDEX(hc_data,1,H6)*cc_data*H7 -> 0 | I46: =-INDEX(hc_data,1,I6)*cc_data*I7 -> 0 | J46: =-INDEX(hc_data,1,J6)*cc_data*J7 -> 0 | ... BJ46: =-INDEX(hc_data,1,BJ6)*cc_data*BJ7 -> -41327.213
A47: Equipe: Produto / design | B47: R$ | C47: =-INDEX(hc_prod,1,C6)*cc_prod*C7 -> -15000 | D47: =-INDEX(hc_prod,1,D6)*cc_prod*D7 -> -15000 | E47: =-INDEX(hc_prod,1,E6)*cc_prod*E7 -> -15000 | F47: =-INDEX(hc_prod,1,F6)*cc_prod*F7 -> -15000 | G47: =-INDEX(hc_prod,1,G6)*cc_prod*G7 -> -15000 | H47: =-INDEX(hc_prod,1,H6)*cc_prod*H7 -> -15000 | I47: =-INDEX(hc_prod,1,I6)*cc_prod*I7 -> -15000 | J47: =-INDEX(hc_prod,1,J6)*cc_prod*J7 -> -15000 | ... BJ47: =-INDEX(hc_prod,1,BJ6)*cc_prod*BJ7 -> -36465.188
A48: Equipe: Zootecnia/veterinária (conteúdo e benchmark) | B48: R$ | C48: =-INDEX(hc_zoo,1,C6)*cc_zoo*C7 -> -12000 | D48: =-INDEX(hc_zoo,1,D6)*cc_zoo*D7 -> -12000 | E48: =-INDEX(hc_zoo,1,E6)*cc_zoo*E7 -> -12000 | F48: =-INDEX(hc_zoo,1,F6)*cc_zoo*F7 -> -12000 | G48: =-INDEX(hc_zoo,1,G6)*cc_zoo*G7 -> -12000 | H48: =-INDEX(hc_zoo,1,H6)*cc_zoo*H7 -> -12000 | I48: =-INDEX(hc_zoo,1,I6)*cc_zoo*I7 -> -12000 | J48: =-INDEX(hc_zoo,1,J6)*cc_zoo*J7 -> -12000 | ... BJ48: =-INDEX(hc_zoo,1,BJ6)*cc_zoo*BJ7 -> -29172.15
A49: Equipe: Vendas (fixo) | B49: R$ | C49: =-INDEX(hc_sales,1,C6)*cc_sales*C7 -> -9000 | D49: =-INDEX(hc_sales,1,D6)*cc_sales*D7 -> -9000 | E49: =-INDEX(hc_sales,1,E6)*cc_sales*E7 -> -9000 | F49: =-INDEX(hc_sales,1,F6)*cc_sales*F7 -> -9000 | G49: =-INDEX(hc_sales,1,G6)*cc_sales*G7 -> -9000 | H49: =-INDEX(hc_sales,1,H6)*cc_sales*H7 -> -9000 | I49: =-INDEX(hc_sales,1,I6)*cc_sales*I7 -> -9000 | J49: =-INDEX(hc_sales,1,J6)*cc_sales*J7 -> -9000 | ... BJ49: =-INDEX(hc_sales,1,BJ6)*cc_sales*BJ7 -> -32818.669
A50: Equipe: Marketing / comunidade | B50: R$ | C50: =-INDEX(hc_mkt,1,C6)*cc_mkt*C7 -> 0 | D50: =-INDEX(hc_mkt,1,D6)*cc_mkt*D7 -> 0 | E50: =-INDEX(hc_mkt,1,E6)*cc_mkt*E7 -> 0 | F50: =-INDEX(hc_mkt,1,F6)*cc_mkt*F7 -> 0 | G50: =-INDEX(hc_mkt,1,G6)*cc_mkt*G7 -> 0 | H50: =-INDEX(hc_mkt,1,H6)*cc_mkt*H7 -> 0 | I50: =-INDEX(hc_mkt,1,I6)*cc_mkt*I7 -> 0 | J50: =-INDEX(hc_mkt,1,J6)*cc_mkt*J7 -> 0 | ... BJ50: =-INDEX(hc_mkt,1,BJ6)*cc_mkt*BJ7 -> -19448.1
A51: Equipe: Administrativo / financeiro | B51: R$ | C51: =-INDEX(hc_adm,1,C6)*cc_adm*C7 -> 0 | D51: =-INDEX(hc_adm,1,D6)*cc_adm*D7 -> 0 | E51: =-INDEX(hc_adm,1,E6)*cc_adm*E7 -> 0 | F51: =-INDEX(hc_adm,1,F6)*cc_adm*F7 -> 0 | G51: =-INDEX(hc_adm,1,G6)*cc_adm*G7 -> 0 | H51: =-INDEX(hc_adm,1,H6)*cc_adm*H7 -> 0 | I51: =-INDEX(hc_adm,1,I6)*cc_adm*I7 -> 0 | J51: =-INDEX(hc_adm,1,J6)*cc_adm*J7 -> 0 | ... BJ51: =-INDEX(hc_adm,1,BJ6)*cc_adm*BJ7 -> -21879.112
A52: Subtotal equipe fixa | B52: R$ | C52: =SUM(C43:C51) -> -108000 | D52: =SUM(D43:D51) -> -108000 | E52: =SUM(E43:E51) -> -108000 | F52: =SUM(F43:F51) -> -108000 | G52: =SUM(G43:G51) -> -108000 | H52: =SUM(H43:H51) -> -108000 | I52: =SUM(I43:I51) -> -108000 | J52: =SUM(J43:J51) -> -108000 | ... BJ52: =SUM(BJ43:BJ51) -> -326971.18
A53: Comissões de vendas | B53: R$ | C53: =-C9*arpa_base*C7*f_price*s_price*12*comm -> 0 | D53: =-D9*arpa_base*D7*f_price*s_price*12*comm -> 0 | E53: =-E9*arpa_base*E7*f_price*s_price*12*comm -> 0 | F53: =-F9*arpa_base*F7*f_price*s_price*12*comm -> -3605.76 | G53: =-G9*arpa_base*G7*f_price*s_price*12*comm -> -3605.76 | H53: =-H9*arpa_base*H7*f_price*s_price*12*comm -> -3605.76 | I53: =-I9*arpa_base*I7*f_price*s_price*12*comm -> -3605.76 | J53: =-J9*arpa_base*J7*f_price*s_price*12*comm -> -3605.76 | ... BJ53: =-BJ9*arpa_base*BJ7*f_price*s_price*12*comm -> -43828.238
A54: Aquisição: custo variável por fazenda | B54: R$ | C54: =-C9*cac_var*C7 -> 0 | D54: =-D9*cac_var*D7 -> 0 | E54: =-E9*cac_var*E7 -> 0 | F54: =-F9*cac_var*F7 -> -7500 | G54: =-G9*cac_var*G7 -> -7500 | H54: =-H9*cac_var*H7 -> -7500 | I54: =-I9*cac_var*I7 -> -7500 | J54: =-J9*cac_var*J7 -> -7500 | ... BJ54: =-BJ9*cac_var*BJ7 -> -91162.969
A55: Marketing fixo | B55: R$ | C55: =-INDEX(mkt_fix_y,1,C6)*C7*IF(C5>=launch_month-1,1,0) -> 0 | D55: =-INDEX(mkt_fix_y,1,D6)*D7*IF(D5>=launch_month-1,1,0) -> 0 | E55: =-INDEX(mkt_fix_y,1,E6)*E7*IF(E5>=launch_month-1,1,0) -> -5000 | F55: =-INDEX(mkt_fix_y,1,F6)*F7*IF(F5>=launch_month-1,1,0) -> -5000 | G55: =-INDEX(mkt_fix_y,1,G6)*G7*IF(G5>=launch_month-1,1,0) -> -5000 | H55: =-INDEX(mkt_fix_y,1,H6)*H7*IF(H5>=launch_month-1,1,0) -> -5000 | I55: =-INDEX(mkt_fix_y,1,I6)*I7*IF(I5>=launch_month-1,1,0) -> -5000 | J55: =-INDEX(mkt_fix_y,1,J6)*J7*IF(J5>=launch_month-1,1,0) -> -5000 | ... BJ55: =-INDEX(mkt_fix_y,1,BJ6)*BJ7*IF(BJ5>=launch_month-1,1,0) -> -43758.225
A56: Custo do evento anual | B56: R$ | C56: =-IF(MOD(C5-1,12)+1=event_month,INDEX(event_cost_y,1,C6),0) -> 0 | D56: =-IF(MOD(D5-1,12)+1=event_month,INDEX(event_cost_y,1,D6),0) -> 0 | E56: =-IF(MOD(E5-1,12)+1=event_month,INDEX(event_cost_y,1,E6),0) -> 0 | F56: =-IF(MOD(F5-1,12)+1=event_month,INDEX(event_cost_y,1,F6),0) -> 0 | G56: =-IF(MOD(G5-1,12)+1=event_month,INDEX(event_cost_y,1,G6),0) -> 0 | H56: =-IF(MOD(H5-1,12)+1=event_month,INDEX(event_cost_y,1,H6),0) -> 0 | I56: =-IF(MOD(I5-1,12)+1=event_month,INDEX(event_cost_y,1,I6),0) -> 0 | J56: =-IF(MOD(J5-1,12)+1=event_month,INDEX(event_cost_y,1,J6),0) -> 0 | ... BJ56: =-IF(MOD(BJ5-1,12)+1=event_month,INDEX(event_cost_y,1,BJ6),0) -> 0
A57: Despesas gerais e administrativas | B57: R$ | C57: =-INDEX(ga_y,1,C6)*C7 -> -12000 | D57: =-INDEX(ga_y,1,D6)*D7 -> -12000 | E57: =-INDEX(ga_y,1,E6)*E7 -> -12000 | F57: =-INDEX(ga_y,1,F6)*F7 -> -12000 | G57: =-INDEX(ga_y,1,G6)*G7 -> -12000 | H57: =-INDEX(ga_y,1,H6)*H7 -> -12000 | I57: =-INDEX(ga_y,1,I6)*I7 -> -12000 | J57: =-INDEX(ga_y,1,J6)*J7 -> -12000 | ... BJ57: =-INDEX(ga_y,1,BJ6)*BJ7 -> -41327.213
A58: Itens pontuais (jurídico, segurança, lançamento) | B58: R$ | C58: =-SUMIFS(oneoff_v,oneoff_m,C5) -> 0 | D58: =-SUMIFS(oneoff_v,oneoff_m,D5) -> -6000 | E58: =-SUMIFS(oneoff_v,oneoff_m,E5) -> -35000 | F58: =-SUMIFS(oneoff_v,oneoff_m,F5) -> 0 | G58: =-SUMIFS(oneoff_v,oneoff_m,G5) -> -40000 | H58: =-SUMIFS(oneoff_v,oneoff_m,H5) -> -30000 | I58: =-SUMIFS(oneoff_v,oneoff_m,I5) -> -25000 | J58: =-SUMIFS(oneoff_v,oneoff_m,J5) -> 0 | ... BJ58: =-SUMIFS(oneoff_v,oneoff_m,BJ5) -> 0
A59: DESPESAS OPERACIONAIS | B59: R$ | C59: =C52+SUM(C53:C58) -> -120000 | D59: =D52+SUM(D53:D58) -> -126000 | E59: =E52+SUM(E53:E58) -> -160000 | F59: =F52+SUM(F53:F58) -> -136105.76 | G59: =G52+SUM(G53:G58) -> -176105.76 | H59: =H52+SUM(H53:H58) -> -166105.76 | I59: =I52+SUM(I53:I58) -> -161105.76 | J59: =J52+SUM(J53:J58) -> -136105.76 | ... BJ59: =BJ52+SUM(BJ53:BJ58) -> -547047.83
A60: EBITDA (= resultado líquido neste modelo) | B60: R$ | C60: =C41+C59 -> -124000 | D60: =D41+D59 -> -130000 | E60: =E41+E59 -> -164000 | F60: =F41+F59 -> -159543.06 | G60: =G41+G59 -> -196382.5 | H60: =H41+H59 -> -183259.86 | I60: =I41+I59 -> -175174.7 | J60: =J41+J59 -> -147126.56 | ... BJ60: =BJ41+BJ59 -> 561738.25
A61: Memo: headcount fixo | B61: pessoas | C61: =INDEX(hc_dir,1,C6)+INDEX(hc_tl,1,C6)+INDEX(hc_dev,1,C6)+INDEX(hc_data,1,C6)+INDEX(hc_prod,1,C6)+INDEX(hc_zoo,1,C6)+INDEX(hc_sales,1,C6)+INDEX(hc_mkt,1,C6)+INDEX(hc_adm,1,C6) -> 7 | D61: =INDEX(hc_dir,1,D6)+INDEX(hc_tl,1,D6)+INDEX(hc_dev,1,D6)+INDEX(hc_data,1,D6)+INDEX(hc_prod,1,D6)+INDEX(hc_zoo,1,D6)+INDEX(hc_sales,1,D6)+INDEX(hc_mkt,1,D6)+INDEX(hc_adm,1,D6) -> 7 | E61: =INDEX(hc_dir,1,E6)+INDEX(hc_tl,1,E6)+INDEX(hc_dev,1,E6)+INDEX(hc_data,1,E6)+INDEX(hc_prod,1,E6)+INDEX(hc_zoo,1,E6)+INDEX(hc_sales,1,E6)+INDEX(hc_mkt,1,E6)+INDEX(hc_adm,1,E6) -> 7 | F61: =INDEX(hc_dir,1,F6)+INDEX(hc_tl,1,F6)+INDEX(hc_dev,1,F6)+INDEX(hc_data,1,F6)+INDEX(hc_prod,1,F6)+INDEX(hc_zoo,1,F6)+INDEX(hc_sales,1,F6)+INDEX(hc_mkt,1,F6)+INDEX(hc_adm,1,F6) -> 7 | G61: =INDEX(hc_dir,1,G6)+INDEX(hc_tl,1,G6)+INDEX(hc_dev,1,G6)+INDEX(hc_data,1,G6)+INDEX(hc_prod,1,G6)+INDEX(hc_zoo,1,G6)+INDEX(hc_sales,1,G6)+INDEX(hc_mkt,1,G6)+INDEX(hc_adm,1,G6) -> 7 | H61: =INDEX(hc_dir,1,H6)+INDEX(hc_tl,1,H6)+INDEX(hc_dev,1,H6)+INDEX(hc_data,1,H6)+INDEX(hc_prod,1,H6)+INDEX(hc_zoo,1,H6)+INDEX(hc_sales,1,H6)+INDEX(hc_mkt,1,H6)+INDEX(hc_adm,1,H6) -> 7 | I61: =INDEX(hc_dir,1,I6)+INDEX(hc_tl,1,I6)+INDEX(hc_dev,1,I6)+INDEX(hc_data,1,I6)+INDEX(hc_prod,1,I6)+INDEX(hc_zoo,1,I6)+INDEX(hc_sales,1,I6)+INDEX(hc_mkt,1,I6)+INDEX(hc_adm,1,I6) -> 7 | J61: =INDEX(hc_dir,1,J6)+INDEX(hc_tl,1,J6)+INDEX(hc_dev,1,J6)+INDEX(hc_data,1,J6)+INDEX(hc_prod,1,J6)+INDEX(hc_zoo,1,J6)+INDEX(hc_sales,1,J6)+INDEX(hc_mkt,1,J6)+INDEX(hc_adm,1,J6) -> 7 | ... BJ61: =INDEX(hc_dir,1,BJ6)+INDEX(hc_tl,1,BJ6)+INDEX(hc_dev,1,BJ6)+INDEX(hc_data,1,BJ6)+INDEX(hc_prod,1,BJ6)+INDEX(hc_zoo,1,BJ6)+INDEX(hc_sales,1,BJ6)+INDEX(hc_mkt,1,BJ6)+INDEX(hc_adm,1,BJ6) -> 20
A62: Memo: headcount total (fixo + suporte e sucesso) | B62: pessoas | C62: =C61+C33 -> 7 | D62: =D61+D33 -> 7 | E62: =E61+E33 -> 7 | F62: =F61+F33 -> 10 | G62: =G61+G33 -> 10 | H62: =H61+H33 -> 10 | I62: =I61+I33 -> 10 | J62: =J61+J33 -> 10 | ... BJ62: =BJ61+BJ33 -> 44
A63: Caixa
A64: Contas a receber | B64: R$ | C64: =C26*dso/30 -> 0 | D64: =D26*dso/30 -> 0 | E64: =E26*dso/30 -> 0 | F64: =F26*dso/30 -> 2829.4 | G64: =G26*dso/30 -> 3999.2187 | H64: =H26*dso/30 -> 5154.9996 | I64: =I26*dso/30 -> 6296.9111 | J64: =J26*dso/30 -> 7425.1197 | ... BJ64: =BJ26*dso/30 -> 489707.1
A65: Contas a pagar (fornecedores e encargos) | B65: R$ | C65: =-(C40+C59)*dpo/30 -> 82666.667 | D65: =-(D40+D59)*dpo/30 -> 86666.667 | E65: =-(E40+E59)*dpo/30 -> 109333.33 | F65: =-(F40+F59)*dpo/30 -> 112020.84 | G65: =-(G40+G59)*dpo/30 -> 138920.1 | H65: =-(H40+H59)*dpo/30 -> 132483.24 | I65: =-(I40+I59)*dpo/30 -> 129376.95 | J65: =-(J40+J59)*dpo/30 -> 112934.61 | ... BJ65: =-(BJ40+BJ59)*dpo/30 -> 604922.03
A66: Variação do capital de giro | B66: R$ | C66: =-C64+C65 -> 82666.667 | D66: =-(D64-C64)+(D65-C65) -> 4000 | E66: =-(E64-D64)+(E65-D65) -> 22666.667 | F66: =-(F64-E64)+(F65-E65) -> -141.89333 | G66: =-(G64-F64)+(G65-F65) -> 25729.444 | H66: =-(H64-G64)+(H65-G65) -> -7592.6427 | I66: =-(I64-H64)+(I65-H65) -> -4248.1977 | J66: =-(J64-I64)+(J65-I65) -> -17570.553 | K66: =-(K64-J64)+(K65-J65) -> -893.03933 | ... BJ66: =-(BJ64-BI64)+(BJ65-BI65) -> -8796.3044
A67: Fluxo de caixa operacional (antes de aportes) | B67: R$ | C67: =C60+C66 -> -41333.333 | D67: =D60+D66 -> -126000 | E67: =E60+E66 -> -141333.33 | F67: =F60+F66 -> -159684.95 | G67: =G60+G66 -> -170653.05 | H67: =H60+H66 -> -190852.51 | I67: =I60+I66 -> -179422.9 | J67: =J60+J66 -> -164697.11 | ... BJ67: =BJ60+BJ66 -> 552941.94
A68: Caixa acumulado ANTES de aportes | B68: R$ | C68: =C67 -> -41333.333 | D68: =C68+D67 -> -167333.33 | E68: =D68+E67 -> -308666.67 | F68: =E68+F67 -> -468351.62 | G68: =F68+G67 -> -639004.67 | H68: =G68+H67 -> -829857.18 | I68: =H68+I67 -> -1009280.1 | J68: =I68+J67 -> -1173977.2 | K68: =J68+K67 -> -1318985.2 | ... BJ68: =BI68+BJ67 -> 3199564.4
A69: Aportes de capital (tranches) | B69: R$ | C69: =ask*(IF(C5=t1m,t1p,0)+IF(C5=t2m,t2p,0)+IF(C5=t3m,t3p,0)) -> 2115000 | D69: =ask*(IF(D5=t1m,t1p,0)+IF(D5=t2m,t2p,0)+IF(D5=t3m,t3p,0)) -> 0 | E69: =ask*(IF(E5=t1m,t1p,0)+IF(E5=t2m,t2p,0)+IF(E5=t3m,t3p,0)) -> 0 | F69: =ask*(IF(F5=t1m,t1p,0)+IF(F5=t2m,t2p,0)+IF(F5=t3m,t3p,0)) -> 0 | G69: =ask*(IF(G5=t1m,t1p,0)+IF(G5=t2m,t2p,0)+IF(G5=t3m,t3p,0)) -> 0 | H69: =ask*(IF(H5=t1m,t1p,0)+IF(H5=t2m,t2p,0)+IF(H5=t3m,t3p,0)) -> 0 | I69: =ask*(IF(I5=t1m,t1p,0)+IF(I5=t2m,t2p,0)+IF(I5=t3m,t3p,0)) -> 0 | J69: =ask*(IF(J5=t1m,t1p,0)+IF(J5=t2m,t2p,0)+IF(J5=t3m,t3p,0)) -> 0 | ... BJ69: =ask*(IF(BJ5=t1m,t1p,0)+IF(BJ5=t2m,t2p,0)+IF(BJ5=t3m,t3p,0)) -> 0
A70: CAIXA FINAL (com aportes) | B70: R$ | C70: =C67+C69 -> 2073666.7 | D70: =C70+D67+D69 -> 1947666.7 | E70: =D70+E67+E69 -> 1806333.3 | F70: =E70+F67+F69 -> 1646648.4 | G70: =F70+G67+G69 -> 1475995.3 | H70: =G70+H67+H69 -> 1285142.8 | I70: =H70+I67+I69 -> 1105719.9 | J70: =I70+J67+J69 -> 941022.82 | K70: =J70+K67+K69 -> 796014.78 | ... BJ70: =BI70+BJ67+BJ69 -> 7899564.4
A71: Flag: EBITDA positivo | B71: 0/1 | C71: =IF(C60>0,1,0) -> 0 | D71: =IF(D60>0,1,0) -> 0 | E71: =IF(E60>0,1,0) -> 0 | F71: =IF(F60>0,1,0) -> 0 | G71: =IF(G60>0,1,0) -> 0 | H71: =IF(H60>0,1,0) -> 0 | I71: =IF(I60>0,1,0) -> 0 | J71: =IF(J60>0,1,0) -> 0 | ... BJ71: =IF(BJ60>0,1,0) -> 1
A72: Flag: caixa acumulado >= 0 após o ponto mínimo | B72: 0/1 | C72: =IF(AND(C68>=0,C5>Retornos!$B$8),1,0) -> 0 | D72: =IF(AND(D68>=0,D5>Retornos!$B$8),1,0) -> 0 | E72: =IF(AND(E68>=0,E5>Retornos!$B$8),1,0) -> 0 | F72: =IF(AND(F68>=0,F5>Retornos!$B$8),1,0) -> 0 | G72: =IF(AND(G68>=0,G5>Retornos!$B$8),1,0) -> 0 | H72: =IF(AND(H68>=0,H5>Retornos!$B$8),1,0) -> 0 | I72: =IF(AND(I68>=0,I5>Retornos!$B$8),1,0) -> 0 | J72: =IF(AND(J68>=0,J5>Retornos!$B$8),1,0) -> 0 | ... BJ72: =IF(AND(BJ68>=0,BJ5>Retornos!$B$8),1,0) -> 1

Sheet Memória de cálculo
A1: Memória de cálculo (lógica de cada linha do modelo mensal)
A3: Linha | B3: Fórmula / lógica | C3: Premissas usadas
A4: Novas fazendas | B4: Zero antes do lançamento; depois = novas/mês do ano x multiplicador do cenário. | C4: launch_month, new_farms_y, f_new
A5: Fazendas perdidas | B5: Fazendas ativas do mês anterior x churn mensal x multiplicadores. | C5: churn_m, f_churn, s_churn
A6: Fazendas ativas | B6: Anterior + novas - perdidas.
A7: Vacas atendidas | B7: Fazendas ativas x vacas médias por fazenda (média ponderada pelo mix). | C7: mix_*, herd_*
A8: ARPA de assinatura | B8: Média ponderada de MAIOR(mínimo do plano; vacas do plano x preço por vaca), x reajuste IPCA do ano x multiplicadores de preço. | C8: mix, herd, p_*, min_*, reajuste, f_price, s_price
A9: Assinatura | B9: Fazendas ativas médias do mês x ARPA.
A10: Implantação | B10: Novas fazendas x implantação média ponderada x reajuste. | C10: set_*
A11: Módulos premium / Benchmark | B11: Fazendas médias x % de adoção do ano x preço x reajuste. | C11: adopt_*_y, price_mod, price_bench
A12: Licenças de consultor | B12: Acumulado de novas licenças/mês (a partir do mês 13) x preço. | C12: new_cons_y, price_cons
A13: Evento | B13: Receita anual lançada no mês do evento. | C13: event_rev_y, event_month
A14: Patrocínios | B14: Valor anual / 12, a partir do lançamento. | C14: spons_y
A15: Tributos | B15: Receita bruta x alíquota do ano. | C15: tax_y
A16: N1 | B16: ARREDONDAR.PARA.CIMA(fazendas ativas / fazendas por N1). | C16: r_n1
A17: CS | B17: MÁXIMO(1; ARREDONDAR.PARA.CIMA(fazendas / fazendas por CS)). | C17: r_cs
A18: N2 zootécnico | B18: ARREDONDAR.PARA.CIMA(vacas atendidas / vacas por analista). | C18: r_n2
A19: Implantação (equipe) | B19: ARREDONDAR.PARA.CIMA(novas fazendas do mês / novas por especialista). | C19: r_onb
A20: Custo de suporte | B20: (N1 x custo + CS x custo + N2 x custo + implantação x custo) x reajuste. | C20: c_*
A21: Ferramentas | B21: (Pessoas de suporte x licença + fazendas médias x custo por fazenda) x reajuste. | C21: tool_seat, tool_farm
... A28: Capital de giro | B28: Receber = receita líquida x prazo/30; Pagar = (custos + despesas) x prazo/30; variação mensal entra no fluxo. | C28: dso, dpo
A29: Fluxo operacional | B29: EBITDA + variação do capital de giro.
A30: Caixa | B30: Caixa anterior + fluxo operacional + aportes (tranches = aporte x % em 3 meses definidos). | C30: ask, t1..t3
A31: Balanço | B31: Ativo (caixa + a receber) = Passivo (a pagar) + capital integralizado + lucros acumulados. Conferência = 0.
A32: Break-even operacional | B32: Primeiro mês com EBITDA > 0.
A33: Payback | B33: Primeiro mês, após o ponto mínimo, em que o caixa acumulado (antes de aportes) volta a >= 0.
A34: VPL | B34: Fluxos operacionais anuais descontados à TMA; versão com valor residual soma múltiplo x receita líquida do ano 5. | C34: disc, tv_mult
A35: TIR | B35: Taxa interna de retorno dos mesmos fluxos anuais.
A36: CAC | B36: (Equipe de vendas fixa + comissão + aquisição variável + marketing fixo) / novas fazendas do ano.
A37: LTV | B37: Contribuição mensal por fazenda (ARPA - custo variável por fazenda) / churn mensal.
A38: Payback do CAC | B38: CAC / contribuição mensal por fazenda.
A39: Suporte por escala | B39: Aba Suporte: aplica as mesmas razões de capacidade e custos às fazendas informadas. | C39: r_*, c_*
